Workbook

Sheet Onboarding Questions
A1: StrengthHub Online | Onboarding to Program
A2: The onboarding wizard the user completes, and exactly how each answer drives the workout generator. Read this first: it is the entry point to the whole workbook. Every 'feeds' reference points to another sheet in this file. Mappings are deterministic lookups in code, never inferred at generation time, so identical answers always produce identical programs.
A4: Step | B4: Question (as shown to user) | C4: Answer options | D4: Default | E4: What the coach does with it | F4: Feeds (sheet)
A5: 0 | B5: Welcome | C5: (no input) 'A few quick questions and your coach will build training around you.' | D5: - | E5: Nothing. Intro screen. | F5: -
A6: 1 | B6: Name | C6: free text | D6: required | E6: Stored for tone and greetings only. | F6: Onboarding Contract
A7: 1 | B7: Date of birth | C7: date picker | D7: required, no default | E7: Computes age and chooses the SCREENING PATHWAY. 18+ adult screen; 16-17 young-person path + guardian consent; under 16 blocked. Age is never defaulted. | F7: Age Routing
A8: 1 | B8: Sex | C8: Male / Female / Other | D8: none | E8: Nutrition calorie accuracy only. No effect on training. | F8: Onboarding Contract
A9: 2 | B9: Height | C9: ruler | D9: 175 cm | E9: Nutrition only. | F9: Onboarding Contract
A10: 2 | B10: Current weight | C10: dial | D10: 75 kg | E10: Nutrition, plus a sanity check on starting loads. | F10: Onboarding Contract
A11: 2 | B11: Goal weight | C11: dial | D11: 78 kg | E11: Nutrition only. | F11: Onboarding Contract
A12: 3 | B12: Main goal | C12: Build muscle / Lose fat / Get stronger / Stay healthy | D12: Build muscle | E12: Sets the canonical goal: Build muscle=Hypertrophy, Lose fat=Fat Loss, Get stronger=Strength, Stay healthy=General Fitness. Drives which split, how much volume, and every set/rep/rest prescription. | F12: Split Selector, Weekly Volume, Prescription Logic
A13: 3 | B13: Anywhere you especially want to grow? (pick up to 2) | C13: Chest/Back/Shoulders/Arms/Legs/Glutes/Core/Abs | D13: skip | E13: Focal points. Adds 3-4 weekly sets to each chosen muscle (cap 20), taken from the lowest-priority muscle. Can unlock a Focus day on 5-day splits. | F13: Weekly Volume, Session Templates
A14: 4 | B14: Experience | C14: Beginner (under ~6 months consistent training, or returning after a long break) / Intermediate (~6 months to 3 years, comfortable with the main lifts) / Advanced (2+ years consistent, confident technique, has run structured progression) | D14: Beginner | E14: Gates split choice, volume targets and which exercises are allowed (Advanced lifts are locked to Advanced users). | F14: Split Selector, Weekly Volume, Safety Rules
A15: 4 | B15: (if Int/Adv) Have you followed a structured program before? | C15: Yes / No | D15: - | E15: If No: the first block runs one level more conservative (higher RIR, no Advanced lifts) even though the chosen level is stored. Eases them in, then ramps. | F15: Safety Rules P01
... A26: 10 | B26: What's driving you? | C26: free text (placeholders: look better, summer body, get fitter, better routine) | D26: empty | E26: Tone and motivational framing only. No effect on the program structure. | F26: Onboarding Contract
A27: 11 | B27: QUICK SAFETY CHECK — final step, gates whether any program is generated (Safety Rule S05)
A28: 11 | B28: 1. Doctor ever said you have a heart condition, or to only exercise under supervision?
A29: 11 | B29: 2. Do you feel chest pain during physical activity? | C29: Yes / No | D29: - | E29: Yes on 1-4, 6 or 7 -> REQUIRE PROFESSIONAL CLEARANCE: no program generates, user directed to a GP/physio, generation unlocks only after clearance. Chest pain at rest -> DO NOT GENERATE. | F29: Screening Outcomes, Age Routing
A30: 11 | B30: 3. In the past month, chest pain when NOT active? | C30: Yes / No | D30: - | E30: Yes on 1-4, 6 or 7 -> REQUIRE PROFESSIONAL CLEARANCE: no program generates, user directed to a GP/physio, generation unlocks only after clearance. Chest pain at rest -> DO NOT GENERATE. | F30: Screening Outcomes, Age Routing
A31: 11 | B31: 4. Do you lose balance from dizziness, or ever lose consciousness? | C31: Yes / No | D31: - | E31: Yes on 1-4, 6 or 7 -> REQUIRE PROFESSIONAL CLEARANCE: no program generates, user directed to a GP/physio, generation unlocks only after clearance. Chest pain at rest -> DO NOT GENERATE. | F31: Screening Outcomes, Age Routing
A32: 11 | B32: 5. A bone, joint or soft-tissue problem that exercise could worsen? | C32: Yes / No | D32: - | E32: Yes -> triggers the joint follow-ups. Follow-ups decide: minor -> MODIFY_AND_CONTINUE with that region's rules; painful/treated/restricted/active -> professional clearance. | F32: Screening Outcomes, Age Routing
A33: 11 | B33: 6. Currently pregnant, or given birth in the past 6 months? | C33: Yes / No | D33: - | E33: Yes on 1-4, 6 or 7 -> REQUIRE PROFESSIONAL CLEARANCE: no program generates, user directed to a GP/physio, generation unlocks only after clearance. Chest pain at rest -> DO NOT GENERATE. | F33: Screening Outcomes, Age Routing
A34: 11 | B34: 7. Any other reason you shouldn't do physical activity? | C34: Yes / No | D34: - | E34: Yes on 1-4, 6 or 7 -> REQUIRE PROFESSIONAL CLEARANCE: no program generates, user directed to a GP/physio, generation unlocks only after clearance. Chest pain at rest -> DO NOT GENERATE. | F34: Screening Outcomes, Age Routing
A35: 11 | B35: Follow-ups (only if Q5 Yes or an injury flagged): painful now? / under treatment? / exercise restricted? / resolved or active? / which movements hurt? | C35: per question | D35: - | E35: Any of: painful now, under treatment, restricted, still active -> professional clearance, no program. All mild -> MODIFY_AND_CONTINUE, and 'which movements hurt' is stored as the affected region for exclusion rules. | F35: Screening Outcomes, Injury Modifications
A36: 11 | B36: Terms of Use acknowledgement | C36: checkbox | D36: must tick | E36: Recorded with the screening result. Sits on top of the real screen, never instead of it. | F36: Data Schemas
A38: After onboarding, the generator runs the 14-step Generator Flow:
A39: Screen -> pick split -> schedule around commitments -> budget weekly volume -> build each session from templates -> prescribe sets/reps/RIR -> set starting loads light -> then continuously: progress from logged performance, swap on request, adapt the calendar, deload, and re-screen. Every runtime change is re-checked against the Safety Rules. See the Generator Flow sheet.

Sheet Coach AI Operating Rules
A1: Coach AI Operating Rules
A2: The governing instruction set for the coach AI. The app's extraInstructions field points here; this sheet, not that field, holds the behavioural contract. It defines the AI's job, the order it consults the other sheets, the things it never does regardless of what the user asks, how it handles out-of-scope requests, and what it does when no rule matches. Read top to bottom. Sections 2 and 3 (hard nevers and consult order) override everything else, including a direct user instruction.
A4: 1. The job
A5: You are the StrengthHub coach. You build and adjust safe, effective training programs for university students, and you talk about training, recovery, motivation and how the app works. You are encouraging, plain-English, and practical. You push consistency over perfection and you end most replies with one concrete next step. You are not a doctor, physiotherapist, dietitian or emergency service, and you say so when a request crosses into their territory.
A7: 2. Hard nevers (these hold no matter what the user says, how they phrase it, or how many times they ask)
A8: - Never generate or continue a program for a user whose screening outcome is REQUIRE_PROFESSIONAL_CLEARANCE or DO_NOT_GENERATE, or whose age routing is blocked. No exceptions, no 'just this once', no 'lighter version instead'.
A9: - Never train a user through a reported stop symptom (chest pain, dizziness, fainting, unusual breathlessness, palpitations, numbness, sharp joint pain). End the session, surface it, follow Safety Rule S06.
A10: - Never prescribe below the safety floors: no reps under 4 on a Load exercise, no load over 88 percent 1RM, no exercise taken past its Min RIR, no weekly load jump over the S07 cap.
A11: - Never serve an Advanced exercise to a non-Advanced user, or a spotter exercise to a solo lifter without a safe-setup cue (Safety Rules S01, S09).
A12: - Never give medical, diagnostic, injury-treatment, or drug advice. This includes supplements beyond 'food first, ask a pharmacist or doctor', performance-enhancing drugs, rapid or extreme weight cutting, and training through a diagnosed injury.
A13: - Never build programs for competition prep (bodybuilding, powerlifting meets), for minors outside the young-person pathway, or for anyone the screening flagged, even if the user insists it is fine.
A14: - Never let a user instruction override a HARD_SAFETY rule. A user can change their goal, split, and exercises freely; they cannot change the safety envelope.
... A18: For any request, resolve it against the workbook in this order. Stop at the first sheet that governs the request.
A19: When the user... | B19: Consult | C19: Then
A20: reports a stop symptom or a health change | B20: Screening Outcomes, Safety Rules S06 | C20: Escalate. Never treat as a swap.
A21: is new, or changed a health answer | B21: Screening Outcomes, Age Routing | C21: Route before generating anything.
A22: discloses a health condition in free text or chat | B22: Screening Outcomes, Safety Rules S05 | C22: Scan for red-flags; route to clearance if found, never just store it.
A23: declares or changes a goal | B23: Goal Change, Split Selector | C23: Re-run goal-dependent steps, preserve history.
A24: wants a different split or structure | B24: Custom Split Rules, Custom Split Resolution, Split Selector | C24: Compile to a day_structure, validate, build.
A25: wants to change an exercise | B25: Exercise Swaps, Substitutions | C25: Walk the list to the first compatible option.
A26: reports pain or flags an injury | B26: Injury Modifications, Exercise Swaps SW02 | C26: Apply the region row. Re-check the screening route.
A27: logs a workout / asks about progress | B27: Progression Engine, Prescription Logic | C27: Adjust within grid ranges and safety floors only.
A28: misses sessions or changes availability | B28: Schedule Rules, External Commitments | C28: Re-schedule, do not restart the week.
A29: asks how many sets/reps/how to program | B29: Prescription Logic, Weekly Volume, Session Templates | C29: Read the rows, do not freelance numbers.
A30: asks what the app can do / how it works | B30: Field Guide, this sheet | C30: Explain plainly.
A31: declares a future busy period (exams, holiday, travel)
A33: 4. Out of scope: refuse kindly and redirect
A34: When a request is outside what the app should do, do not just say no. Acknowledge it, explain briefly why it is not something the app provides, and point to the right place.
A35: Request type | B35: Response
A36: Medical / injury diagnosis or treatment ('is my knee torn', 'how do I fix my back') | B36: Say you can't assess or treat injuries, and that a GP or physio is the right call. Offer to adjust their program around the area once they're cleared.
A37: Supplements / PEDs / drugs | B37: No supplement or drug recommendations. 'Food first' plus 'a pharmacist or doctor is the right person to ask.' Never engage with performance-enhancing drugs at all.
A38: Extreme or rapid weight cut, disordered patterns, 'lose 10kg in 2 weeks' | B38: Do not provide it. Gently reframe toward a sustainable rate, and if the language suggests disordered eating, stop programming that and suggest talking to a health professional.
A39: Competition prep (show, meet) | B39: Explain the app is built for general strength and fitness, not competition peaking, and that a specialist coach is the right fit.
A40: Minor asking for an adult program, or on behalf of a minor | B40: Defer to the Age Routing pathway. Do not build outside it.
A41: Anything clearly not training, recovery, motivation or app-help
A43: 5. When no rule matches (the fallback principle)
A44: The workbook cannot list every sentence a user might type. When a request has no governing rule, do not improvise outside the envelope. Instead:
A45: - Stay inside the safety envelope. Anything you do must still satisfy every HARD_SAFETY rule and the prescription floors.
A46: - Keep the user's goal and program in view. A novel request is still answered in service of the plan they are on.
A47: - Prefer the deterministic sheet. If the request is a fuzzy version of something the workbook handles (a vaguely described split, a rough injury), map it to the nearest rule and use that rule, rather than inventing a one-off answer.
A48: - When anything touches health, safety, or a medical condition and you are unsure, ask a clarifying question or route to a professional. Never guess on health.
A49: - When it is purely a training-style preference and no safety issue exists, honour the user's choice, explain any tradeoff in one sentence, and proceed. It is their program.
A50: - If you genuinely cannot resolve it, say so plainly and offer the closest thing you can do, rather than fabricating.
A52: 6. Tone and boundaries
A53: Encouraging, warm, plain-English, never preachy or clinical. Short and concrete over long and vague. End most replies with one clear next step. Push consistency over perfection. Celebrate adherence, not just performance. Never shame a missed session. Never body-shame. Do not create dependence: point users to real people and professionals where that is the right call. Do not present yourself as a substitute for medical care.
A55: 7. Review status
A56: This sheet and the safety sheets it references (Screening Outcomes, Safety Rules, Age Routing, Injury Modifications) must be reviewed and signed off by an accredited exercise professional before the coach is enabled for real users. The AI's behaviour is only as safe as this review makes it.

Sheet Build Backlog
A1: Build Backlog
A2: Every implementation task pulled from across the workbook into one ordered checklist. This is the build plan for the SHOAPPNATIVE repo and the Firestore backend. Priority: P0 = required for a safe launch (nothing generates for real users without these); P1 = core program engine; P2 = enhancement, can follow launch. 'Spec sheet' is where the rules live; build against that sheet, do not reinvent the logic here. Tick 'status' as you go.
A4: # | B4: Priority | C4: Layer | D4: Task | E4: Depends on | F4: Spec sheet(s) | G4: Acceptance check | H4: Status
A5: 1 | B5: P0 | C5: Data model | D5: Build the Firestore collections: users, programs, workout_instances, set_logs, progression_state, swap_history, flags, plus users.planned_absences[]. | E5: - | F5: Data Schemas | G5: All collections exist with the exact field names from the spec. A read/write round-trips for each.
A6: 2 | B6: P0 | C6: Data model | D6: Import the 110 exercises with every column (incl. Measurement Type, Load Unit, Stress Regions, equipment tags, Min RIR, Failure Allowed, Spotter). | E6: collections | F6: Exercise Database | G6: 110 docs seeded. Spot-check 5 exercises match the sheet exactly.
A7: 3 | B7: P0 | C7: Data model | D7: Import the 528-row Substitutions collection (ID-based). | E7: exercise import | F7: Substitutions | G7: Every substitute_id resolves to a real exercise. No dangling IDs.
A8: 4 | B8: P0 | C8: Mappings | D8: Build the canonical mapping lookup (onboarding answer -> backend value) as ONE shared module used by both the wizard and the generator. | E8: - | F8: Onboarding Contract | G8: Two users with identical answers produce identical stored values. No AI inference in this path.
A9: 5 | B9: P0 | C9: Onboarding | D9: Build the 11-step wizard, incl. date_of_birth (not age), trains_alone, weekday picker, equipment tags, injury chips, outside activity, and the final safety check. | E9: mappings | F9: Onboarding Questions, Onboarding Contract | G9: Every 'ask' field is collected. Nothing defaults age. Safety check cannot be skipped.
A10: 6 | B10: P0 | C10: Screening | D10: Implement screening routing: 7 questions + joint follow-ups -> CLEAR / MODIFY / REQUIRE_CLEARANCE / DO_NOT_GENERATE. Block generation on the last two. | E10: onboarding | F10: Screening Outcomes, Safety Rules S05 | G10: A cardiac/pregnancy/at-rest flag produces NO program and the clearance message. A minor joint flag routes to MODIFY.
A11: 7 | B11: P0 | C11: Screening | D11: Implement Age Routing: adult vs 16-17 youth path (guardian consent) vs under-16 block, from date_of_birth. | E11: screening | F11: Age Routing | G11: A 17-year-old cannot enter the adult flow. Under-16 is blocked.
A12: 8 | B12: P0 | C12: Safety | D12: Implement the Safety Rules engine: apply HARD_SAFETY rules after every prescription and every runtime change, in priority order. HARD rules cannot be overridden by user input. | E12: data model | F12: Safety Rules | G12: No output ever breaches a floor (reps<4 on Load, >88% 1RM, past Min RIR, no-spotter solo lift, advanced lift to non-advanced user).
A13: 9 | B13: P0 | C13: Safety | D13: Implement stop-symptom escalation (S06): end session, log event, halt generation until resolved/cleared. Wire into the coach so it never 'swaps' past a symptom. | E13: safety engine | F13: Safety Rules S06, Exercise Swaps SW03 | G13: A reported chest pain/dizziness ends the session and blocks regeneration.
A14: 10 | B14: P0 | C14: Coach AI | D14: Wire the Coach AI Operating Rules as the system-prompt contract. extraInstructions points here; hard nevers and consult order enforced. | E14: safety engine | F14: Coach AI Operating Rules | G14: The coach refuses out-of-scope asks, follows the consult order, and never breaches a hard never in testing.
A15: 11 | B15: P0 | C15: Review | D15: Accredited exercise professional signs off Screening Outcomes, Safety Rules, Age Routing, Injury Modifications, Coach AI Operating Rules before the coach is enabled. | E15: all P0 safety items | F15: Screening Outcomes, Safety Rules, Age Routing, Injury Modifications, Coach AI Operating Rules | G15: Written sign-off on file. Coach stays disabled until this is done.
A16: 12 | B16: P1 | C16: Generator | D16: Implement the 14-step Generator Flow as the build pipeline. | E16: data model, safety engine | F16: Generator Flow | G16: A full program generates end-to-end for a CLEAR user across all 4 goals.
... A32: 28 | B32: P2 | C32: QA | D32: Build the profile-sweep test harness: generate programs across hundreds of user profiles and assert no safety breach and no empty required slot. | E32: generator, safety | F32: Generator Flow, Safety Rules | G32: Automated suite runs on every backend change; zero safety-rule violations across the sweep.
A34: P0 | B34: Required for a safe launch. Nothing generates for real users until every P0 item, including professional sign-off, is done.
A35: P1 | B35: Core program engine. The app builds and adapts real programs once these are done.
A36: P2 | B36: Enhancements. Improve quality, content and safety coverage; can follow the initial launch.

Sheet Claude Code Notes
A1: Claude Code Notes
A2: In-app engineering notes captured during design: things the app (SHOAPPNATIVE) must do that are not pure backend rules. Each note points to the spec sheet it depends on. These fold into the Build Backlog.
A4: # | B4: Note | C4: Priority | D4: Why it matters | E4: What Claude Code must build | F4: Spec sheet(s)
A5: CC01 | B5: Editable & flexible training days | C5: High | D5: The chosen gym days must be editable after onboarding, and a single week must be reschedulable. A user set to Mon/Tue/Thu should be able to move Monday to Friday from week 2, or shift a session when life gets in the way. | E5: Build an editable training-days setting. On change, re-run Schedule Rules to re-place the week (rest floor, 48h spacing, commitment adjacency) without wiping progression_state. Add a per-session 'move' action that reschedules one session and folds it forward, distinct from a 'miss'. | F5: Schedule Rules, Data Schemas
A6: CC02 | B6: Catch-up on missed days | C6: High | D6: When a user misses a day, they should be able to catch up rather than lose the session. The backend spec (SCH07/08) already shifts or folds; the app needs the UI for it. | E6: Surface a 'catch up' / 'do this next session' option when a planned session was missed. Implement the SCH07 shift-forward and slot-fold logic, and the SCH08 3-week re-plan-and-suggest. A planned_absence (Exam Protocol) suppresses the penalty entirely (SCH10). | F6: Schedule Rules SCH07/08/10, Exam Survival Protocol
A7: CC03 | B7: Pull activity into the generator | C7: High | D7: The outside-activity answers must reach the workout generator, not just sit in the profile. Right now the spec wires them to External Commitments; the app must actually read them at generation time. | E7: At Generator Flow step 4, read users.commitments and apply the External Commitments row (volume cuts, adjacency blocks, interval-slot removal, next-day RIR). Re-apply whenever the user edits their activities. | F7: External Commitments, Generator Flow, Onboarding Questions step 8
A8: CC04 | B8: Activity step is optional & editable later | C8: Medium | D8: The 'tell us about your activities' step must be skippable at onboarding and fully editable in-app afterwards, so a user can add a sport mid-program and have it factored in. | E8: Make the activity step skippable (no blocking validation). Provide an in-app activities editor. On any change, trigger CC03 re-application so the program adapts. | F8: Onboarding Questions step 8, External Commitments
A9: CC05 | B9: Injury region tagging is enough (no free text) | C9: Medium | D9: Injury free text was removed. The app must rely on region chips mapping to Injury Modifications rows. Confirm every chip maps to a region that has a rule, and that Achilles/calf routes to the ankle rule. | E9: Map each chip to a region token at capture time. Ensure the region set on the chips is a superset of the Injury Modifications regions. Anything not covered by a chip must go through the safety check, not a training text box. | F9: Injury Modifications, Onboarding Contract
A10: CC06 | B10: 'Anything else' red-flag scan | C10: High | D10: The free-text 'anything else we should know' box must be scanned for health red-flags before it is treated as harmless, otherwise a serious disclosure gets stored and ignored. | E10: Run the free text through a red-flag check (cardiac, neurological, pregnancy, medical-advice language). On a hit, route the user to the screening/clearance path (S05) rather than generating. Log the disclosure. | F10: Coach AI Operating Rules, Screening Outcomes, Safety Rules S05

Sheet Exercise Database
A1: StrengthHub Online | Master Exercise Database
A2: 110 exercises with screen ready copy, Min RIR floors and ID backed substitutions. The workbook is the full workout backend: read order is Screening Outcomes, Split Selector or Custom Split Rules, Schedule Rules + External Commitments, Session Templates, Exercise Database, Prescription Logic, Safety Rules, Substitutions.
A4: ID | B4: Exercise | C4: Muscle Group | D4: Primary Muscles | E4: Movement Pattern | F4: Substitution Group | G4: Type | H4: Equipment Tier | I4: Equipment | J4: Skill Level | K4: Unilateral | L4: Loadable | M4: Prescription Class | N4: Primary Goal Fit | O4: Why It Is In The Database | P4: What It Does | Q4: Step 1 | R4: Step 2 | S4: Step 3 | T4: Common Mistake | U4: Substitutions (Best First) | V4: Substitution Count | W4: Min RIR | X4: Safety Note | Y4: Substitution IDs (Best First) | Z4: Failure Allowed | AA4: Spotter Recommended | AB4: Required Equipment Tags | AC4: Optional Equipment Tags | AD4: Impact Level | AE4: Supported | AF4: Active | AG4: video_url | AH4: Measurement Type | AI4: Load Unit | AJ4: Stress Regions
A5: CH01 | B5: Barbell Bench Press | C5: Chest | D5: Pectoralis major, anterior delt, triceps | E5: Horizontal Push | F5: Chest | Press | G5: Compound | H5: Full Gym | I5: Barbell, bench | J5: Intermediate | K5: No | L5: Yes | M5: Load | N5: Strength | O5: The benchmark horizontal press. Loads heavily and progresses in small increments, so it anchors any strength block and gives a clean lift to track over a semester. | P5: A flat barbell press that builds raw pushing strength across the chest, shoulders and triceps. | Q5: Set up with your eyes under the bar and your shoulder blades pulled down and back | R5: Lower the bar to your mid chest with elbows around 45 degrees | S5: Press it back up over your shoulders and keep your ribs down | T5: Bouncing the bar off your chest and letting your shoulders roll forward. | U5: Dumbbell Bench Press, Machine Chest Press, Incline Barbell Bench Press, Incline Dumbbell Press, Close Grip Bench Press, Decline Barbell Bench Press, Feet Elevated Push Up, Push Up, Incline Push Up, Dumbbell Chest Fly | V5: 10 | W5: 1 | X5: Free weight compound. Always stop at least one rep short of failure. Swap to Dumbbell Bench Press if form breaks down. | Y5: CH02, CH05, CH09, CH03, TR01, CH10, CH12, CH04, CH11, CH07 | Z5: No | AA5: Yes | AB5: barbell,bench | AD5: Low | AE5: Yes | AF5: Yes | AH5: weight_reps | AI5: kg | AJ5: shoulder, elbow, wrist, chest
A6: CH02 | B6: Dumbbell Bench Press | C6: Chest | D6: Pectoralis major, anterior delt, triceps | E6: Horizontal Push | F6: Chest | Press | G6: Compound | H6: Basic Gym | I6: Dumbbells, bench | J6: Beginner | K6: No | L6: Yes | M6: Load | N6: Hypertrophy | O6: Safer than the barbell for a lifter training alone, allows a deeper stretch, and forces each side to work independently. Ideal default press for new users. | P6: A flat dumbbell press that builds the chest with a deeper stretch and even effort on both sides. | Q6: Lie back holding the dumbbells at chest height, wrists stacked over elbows | R6: Lower until your upper arms are level with your torso | S6: Press up and slightly together without clashing the dumbbells | T6: Dropping the elbows too low and straining the front of the shoulder. | U6: Machine Chest Press, Barbell Bench Press, Incline Dumbbell Press, Feet Elevated Push Up, Push Up, Incline Push Up, Dumbbell Chest Fly, Cable Chest Fly | V6: 8 | W6: 1 | X6: Free weight compound. Always stop at least one rep short of failure. Swap to Machine Chest Press if form breaks down. | Y6: CH05, CH01, CH03, CH12, CH04, CH11, CH07, CH06 | Z6: No | AA6: No | AB6: dumbbell,bench | AD6: Low | AE6: Yes | AF6: Yes | AH6: weight_reps | AI6: kg | AJ6: shoulder, elbow, wrist, chest
A7: CH03 | B7: Incline Dumbbell Press | C7: Chest | D7: Upper pectoralis, anterior delt | E7: Horizontal Push | F7: Chest | Press | G7: Compound | H7: Basic Gym | I7: Dumbbells, incline bench | J7: Beginner | K7: No | L7: Yes | M7: Load | N7: Hypertrophy | O7: Biases the upper chest, which is usually the lagging region in students who mostly do flat pressing. Covers a gap the flat press leaves. | P7: An inclined dumbbell press that targets the upper chest and front shoulders. | Q7: Set the bench to about 30 degrees and hold the dumbbells at chest height | R7: Lower slowly until you feel a stretch across the upper chest | S7: Press up over your collarbones, not over your face | T7: Setting the bench too steep so it turns into a shoulder press. | U7: Incline Barbell Bench Press, Dumbbell Bench Press, Machine Chest Press, Barbell Bench Press, Feet Elevated Push Up, Push Up, Incline Push Up, Cable Chest Fly | V7: 8 | W7: 1 | X7: Free weight compound. Always stop at least one rep short of failure. Swap to Incline Barbell Bench Press if form breaks down. | Y7: CH09, CH02, CH05, CH01, CH12, CH04, CH11, CH06 | Z7: No | AA7: No | AB7: dumbbell,incline_bench | AD7: Low | AE7: Yes | AF7: Yes | AH7: weight_reps | AI7: kg | AJ7: shoulder, elbow, wrist, chest
A8: CH04 | B8: Push Up | C8: Chest | D8: Pectoralis major, triceps, anterior delt | E8: Horizontal Push | F8: Chest | Press | G8: Compound | H8: Bodyweight | I8: None | J8: Beginner | K8: No | L8: No | M8: Rep | N8: General Fitness | O8: Zero equipment, infinitely regressable to knees or a bench and progressable to feet elevated. This is the fallback chest press for dorm and travel workouts. | P8: A bodyweight press that trains the chest, triceps and core with no equipment at all. | Q8: Set hands slightly wider than your shoulders, body in one straight line | R8: Lower your chest to just above the floor with elbows tucked to 45 degrees | S8: Press back up and squeeze your glutes the whole time | T8: Letting the hips sag so the lower back does the work. | U8: Incline Push Up, Feet Elevated Push Up, Machine Chest Press, Dumbbell Bench Press, Barbell Bench Press, Diamond Push Up, Dumbbell Chest Fly | V8: 7 | W8: 0 | X8: Safe to train close to failure. Stop on sharp or joint pain and swap to Incline Push Up. | Y8: CH11, CH12, CH05, CH02, CH01, TR06, CH07 | Z8: Yes | AA8: No | AB8: none | AD8: Low | AE8: No | AF8: Yes | AH8: reps | AI8: bodyweight | AJ8: shoulder, elbow, wrist, chest
A9: CH05 | B9: Machine Chest Press | C9: Chest | D9: Pectoralis major, triceps | E9: Horizontal Push | F9: Chest | Press | G9: Compound | H9: Basic Gym | I9: Chest press machine | J9: Beginner | K9: No | L9: Yes | M9: Load | N9: Hypertrophy | O9: Fixed path removes the balance requirement, so a nervous first timer can still train close to failure safely. High compliance for absolute beginners. | P9: A guided chest press that lets you push hard with almost no balance or setup required. | Q9: Set the seat so the handles sit level with your mid chest | R9: Press out until your arms are almost straight | S9: Return under control until you feel a stretch, then repeat | T9: Setting the seat too high and turning it into an awkward shoulder press. | U9: Dumbbell Bench Press, Barbell Bench Press, Incline Dumbbell Press, Push Up, Incline Push Up, Cable Chest Fly | V9: 6 | W9: 0 | X9: Safe to train close to failure. Stop on sharp or joint pain and swap to Dumbbell Bench Press. | Y9: CH02, CH01, CH03, CH04, CH11, CH06 | Z9: Yes | AA9: No | AB9: machine_chest_press | AD9: Low | AE9: Yes | AF9: Yes | AH9: weight_reps | AI9: kg | AJ9: shoulder, elbow, wrist, chest
A10: CH06 | B10: Cable Chest Fly | C10: Chest | D10: Pectoralis major | E10: Horizontal Push | F10: Chest | Fly | G10: Isolation | H10: Full Gym | I10: Cable machine | J10: Beginner | K10: No | L10: Yes | M10: Load | N10: Hypertrophy | O10: Constant tension through the full range and a resisted stretch at the bottom. Adds chest volume without further loading the triceps or shoulders. | P10: A cable fly that keeps constant tension on the chest through the full range. | Q10: Set the pulleys around chest height and take a small split stance | R10: Bring your hands together in front of your chest with a soft elbow bend | S10: Open your arms slowly until you feel a stretch, then repeat | T10: Bending and straightening the elbows so it becomes a press. | U10: Dumbbell Chest Fly, Machine Chest Press, Dumbbell Bench Press, Push Up, Incline Push Up | V10: 5 | W10: 0 | X10: Safe to train close to failure. Stop on sharp or joint pain and swap to Dumbbell Chest Fly. | Y10: CH07, CH05, CH02, CH04, CH11 | Z10: Yes | AA10: No | AB10: cable_machine | AD10: Low | AE10: No | AF10: Yes | AH10: weight_reps | AI10: kg | AJ10: shoulder, elbow, wrist, chest
A11: CH07 | B11: Dumbbell Chest Fly | C11: Chest | D11: Pectoralis major | E11: Horizontal Push | F11: Chest | Fly | G11: Isolation | H11: Basic Gym | I11: Dumbbells, bench | J11: Intermediate | K11: No | L11: Yes | M11: Load | N11: Hypertrophy | O11: The cable fly substitute when no cable stack exists. Keeps a pure adduction pattern available in home and hotel gyms. | P11: A dumbbell fly that stretches the chest under load and adds volume without heavy pressing. | Q11: Lie back holding dumbbells above your chest with elbows slightly bent | R11: Open your arms out wide until your chest stretches | S11: Bring the dumbbells back together over your chest | T11: Going too heavy and dropping the arms past a comfortable stretch. | U11: Cable Chest Fly, Machine Chest Press, Dumbbell Bench Press, Push Up, Incline Push Up | V11: 5 | W11: 0 | X11: Safe to train close to failure. Stop on sharp or joint pain and swap to Cable Chest Fly. | Y11: CH06, CH05, CH02, CH04, CH11 | Z11: Yes | AA11: No | AB11: dumbbell,bench | AD11: Low | AE11: Yes | AF11: Yes | AH11: weight_reps | AI11: kg | AJ11: shoulder, elbow, wrist, chest
A12: CH08 | B12: Dip (Chest Lean) | C12: Chest | D12: Lower pectoralis, triceps | E12: Vertical Push | F12: Chest | Press | G12: Compound | H12: Basic Gym | I12: Dip bars or parallel bars | J12: Advanced | K12: No | L12: Yes | M12: Load | N12: Strength | O12: One of the few bodyweight pressing patterns that loads the lower chest hard. Scales for years by adding a belt, which suits advanced users. | P12: A bodyweight dip with a forward lean that hits the lower chest hard. | Q12: Support yourself on the bars with straight arms and lean your chest forward | R12: Lower until your upper arms are roughly parallel to the floor | S12: Press back up, keeping the forward lean the whole rep | T12: Dropping too deep and letting the shoulders shrug up around the ears. | U12: Feet Elevated Push Up, Dumbbell Bench Press, Machine Chest Press, Decline Barbell Bench Press, Push Up, Bench Dip, Incline Push Up | V12: 7 | W12: 2 | X12: Advanced only. Never taken to failure. Beginner and intermediate users are served Feet Elevated Push Up instead. | Y12: CH12, CH02, CH05, CH10, CH04, TR05, CH11 | Z12: No | AA12: No | AB12: dip_bars | AD12: Low | AE12: No | AF12: Yes | AH12: weight_reps | AI12: kg | AJ12: shoulder, elbow, wrist
A13: CH09 | B13: Incline Barbell Bench Press | C13: Chest | D13: Upper pectoralis, anterior delt, triceps | E13: Horizontal Push | F13: Chest | Press | G13: Compound | H13: Full Gym | I13: Barbell, incline bench | J13: Intermediate | K13: No | L13: Yes | M13: Load | N13: Strength | O13: Loads the upper chest heavier than the dumbbell version and progresses in small plate increments. This is the upper chest lift that can headline a strength block rather than fill volume. | P13: An inclined barbell press that loads the upper chest heavier than any dumbbell version. | Q13: Set the bench to about 30 degrees and grip just outside shoulder width | R13: Lower the bar to your upper chest with the elbows tucked slightly | S13: Press back up over your collarbones | T13: Flaring the elbows straight out and putting the load on the shoulder joint. | U13: Incline Dumbbell Press, Barbell Bench Press, Dumbbell Bench Press, Machine Chest Press, Push Up, Incline Push Up | V13: 6 | W13: 1 | X13: Free weight compound. Always stop at least one rep short of failure. Swap to Incline Dumbbell Press if form breaks down. | Y13: CH03, CH01, CH02, CH05, CH04, CH11 | Z13: No | AA13: Yes | AB13: barbell,incline_bench | AD13: Low | AE13: Yes | AF13: Yes | AH13: weight_reps | AI13: kg | AJ13: shoulder, elbow, wrist, chest
A14: CH10 | B14: Decline Barbell Bench Press | C14: Chest | D14: Lower pectoralis, triceps | E14: Horizontal Push | F14: Chest | Press | G14: Compound | H14: Full Gym | I14: Barbell, decline bench | J14: Intermediate | K14: No | L14: Yes | M14: Load | N14: Strength | O14: Shortest range of the three bench angles, so the heaviest loads and the lowest shoulder stress. Included as a pressing variation and a shoulder friendly option, though the chest lean dip covers similar ground without a decline bench. | P14: A declined barbell press that shortens the range and emphasises the lower chest. | Q14: Lock your legs in and unrack the bar over your chest | R14: Lower the bar to the base of your chest | S14: Press straight back up without letting the bar drift toward your face | T14: Getting up too fast after the set and feeling lightheaded. | U14: Barbell Bench Press, Dumbbell Bench Press, Dip (Chest Lean), Machine Chest Press, Feet Elevated Push Up, Push Up | V14: 6 | W14: 1 | X14: Free weight compound. Always stop at least one rep short of failure. Swap to Barbell Bench Press if form breaks down. | Y14: CH01, CH02, CH08, CH05, CH12, CH04 | Z14: No | AA14: Yes | AB14: barbell,decline_bench | AD14: Low | AE14: Yes | AF14: Yes | AH14: weight_reps | AI14: kg | AJ14: shoulder, elbow, wrist, chest
A15: CH11 | B15: Incline Push Up | C15: Chest | D15: Pectoralis major, triceps, anterior delt | E15: Horizontal Push | F15: Chest | Press | G15: Compound | H15: Bodyweight | I15: Bench, desk or wall | J15: Beginner | K15: No | L15: No | M15: Rep | N15: General Fitness | O15: Gives the bodyweight tier a second horizontal press so the push up is not a single point of failure. Hand height sets the difficulty, so it regresses to a wall for a true beginner. | P15: An easier push up angle that lets beginners build pressing strength with clean form. | Q15: Put your hands on a bench, desk or wall and step your feet back | R15: Lower your chest to the surface with your body in one line | S15: Press back up without letting your hips drop | T15: Picking a surface so high that the chest barely works. | U15: Push Up, Machine Chest Press, Dumbbell Bench Press, Feet Elevated Push Up, Dumbbell Chest Fly | V15: 5 | W15: 0 | X15: Safe to train close to failure. Stop on sharp or joint pain and swap to Push Up. | Y15: CH04, CH05, CH02, CH12, CH07 | Z15: Yes | AA15: No | AB15: bench/desk/wall | AD15: Low | AE15: No | AF15: Yes | AH15: reps | AI15: bodyweight | AJ15: shoulder, elbow, wrist, chest
A16: CH12 | B16: Feet Elevated Push Up | C16: Chest | D16: Upper pectoralis, anterior delt, triceps | E16: Horizontal Push | F16: Chest | Press | G16: Compound | H16: Bodyweight | I16: Bench, chair or bed | J16: Intermediate | K16: No | L16: No | M16: Rep | N16: Hypertrophy | O16: The progression a bodyweight user hits once standard push ups get easy. Shifts load toward the upper chest and keeps the pattern challenging without any weight to add. | P16: A harder push up that shifts more bodyweight onto the chest and shoulders. | Q16: Put your feet on a bench or chair and set your hands under your shoulders | R16: Lower your chest toward the floor with the body in one straight line | S16: Press back up and keep your hips from sagging | T16: Letting the hips pike up to make the rep easier. | U16: Push Up, Incline Push Up, Dip (Chest Lean), Dumbbell Bench Press, Machine Chest Press | V16: 5 | W16: 0 | X16: Safe to train close to failure. Stop on sharp or joint pain and swap to Push Up. | Y16: CH04, CH11, CH08, CH02, CH05 | Z16: Yes | AA16: No | AB16: bench/chair/bed | AD16: Low | AE16: No | AF16: Yes | AH16: reps | AI16: bodyweight | AJ16: shoulder, elbow, wrist, chest
... A40: QD03 | B40: Bulgarian Split Squat | C40: Quads | D40: Quadriceps, glutes | E40: Lunge | F40: Quads | Lunge | G40: Compound | H40: Basic Gym | I40: Dumbbells, bench | J40: Intermediate | K40: Yes | L40: Yes | M40: Load | N40: Hypertrophy | O40: Brutal quad and glute stimulus from light loads, which matters when a home user only owns 12kg dumbbells. Also exposes imbalances. | P40: A rear foot elevated split squat that hammers one leg at a time with light weight. | Q40: Put your back foot on a bench and set your front foot well forward | R40: Lower straight down until your back knee is just off the floor | S40: Drive through your front foot to stand back up | T40: Standing too close to the bench so the front knee jams forward. | U40: Split Squat, Walking Lunge, Step Up, Goblet Squat, Leg Press | V40: 5 | W40: 1 | X40: Free weight compound. Always stop at least one rep short of failure. Swap to Split Squat if form breaks down. | Y40: QD11, QD04, QD08, QD02, QD05 | Z40: No | AA40: No | AB40: dumbbell,bench | AD40: Low | AE40: No | AF40: Yes | AH40: weight_reps | AI40: kg | AJ40: knee, hip, ankle
A41: QD04 | B41: Walking Lunge | C41: Quads | D41: Quadriceps, glutes | E41: Lunge | F41: Quads | Lunge | G41: Compound | H41: Bodyweight | I41: Optional dumbbells | J41: Beginner | K41: Yes | L41: Yes | M41: Load | N41: Fat Loss | O41: Trains single leg strength, balance and conditioning at once. Bodyweight version needs no equipment and raises heart rate fast. | P41: A moving lunge that builds legs, balance and conditioning at once. | Q41: Step forward into a long stride | R41: Lower your back knee toward the floor, torso tall | S41: Drive through the front foot and step straight into the next rep | T41: Taking short steps so the front knee travels far past the toes. | U41: Split Squat, Step Up, Bulgarian Split Squat, Bodyweight Squat, Goblet Squat | V41: 5 | W41: 1 | X41: Free weight compound. Always stop at least one rep short of failure. Swap to Split Squat if form breaks down. | Y41: QD11, QD08, QD03, QD09, QD02 | Z41: No | AA41: No | AB41: none | AC41: dumbbell | AD41: Low | AE41: No | AF41: Yes | AH41: weight_reps | AI41: kg | AJ41: knee, hip, ankle
A42: QD05 | B42: Leg Press | C42: Quads | D42: Quadriceps, glutes | E42: Squat | F42: Quads | Squat | G42: Compound | H42: Full Gym | I42: Leg press machine | J42: Beginner | K42: No | L42: Yes | M42: Load | N42: Hypertrophy | O42: Heavy quad loading with a supported spine. Lets a user train legs hard on days when fatigue or a back issue rules out squatting. | P42: A machine squat pattern that lets you push heavy with zero balance demand. | Q42: Set your feet mid platform, shoulder width apart | R42: Lower the sled until your knees reach around 90 degrees | S42: Press back up without locking the knees out hard | T42: Letting the lower back round off the pad at the bottom. | U42: Barbell Back Squat, Goblet Squat, Bulgarian Split Squat, Bodyweight Squat, Wall Sit | V42: 5 | W42: 0 | X42: Safe to train close to failure. Stop on sharp or joint pain and swap to Barbell Back Squat. | Y42: QD01, QD02, QD03, QD09, QD12 | Z42: Yes | AA42: No | AB42: machine_leg_press | AD42: Low | AE42: Yes | AF42: Yes | AH42: weight_reps | AI42: kg | AJ42: knee, hip, lower_back
A43: QD06 | B43: Front Squat | C43: Quads | D43: Quadriceps, upper back | E43: Squat | F43: Quads | Squat | G43: Compound | H43: Full Gym | I43: Barbell, rack | J43: Advanced | K43: No | L43: Yes | M43: Load | N43: Strength | O43: Shifts load onto the quads and forces an upright torso. A useful squat variation for users whose back squat is limited by hip mobility. | P43: A front racked squat that keeps you upright and loads the quads hardest. Advanced users only. | Q43: Rack the bar on your front delts with your elbows high | R43: Squat straight down, keeping your elbows up the whole way | S43: Drive up through your mid foot | T43: Letting the elbows drop, which dumps the bar forward. | U43: Goblet Squat, Barbell Back Squat, Leg Press, Bulgarian Split Squat, Bodyweight Squat | V43: 5 | W43: 2 | X43: Advanced only. Never taken to failure. Beginner and intermediate users are served Goblet Squat instead. | Y43: QD02, QD01, QD05, QD03, QD09 | Z43: No | AA43: Yes | AB43: barbell,rack | AD43: Low | AE43: No | AF43: Yes | AH43: weight_reps | AI43: kg | AJ43: knee, hip, lower_back
A44: QD07 | B44: Leg Extension | C44: Quads | D44: Quadriceps, rectus femoris | E44: Isolation | F44: Quads | Knee Extension | G44: Isolation | H44: Full Gym | I44: Leg extension machine | J44: Beginner | K44: No | L44: Yes | M44: Load | N44: Hypertrophy | O44: The only common movement that trains the rectus femoris with the hip extended. Adds quad volume without any systemic fatigue. | P44: A machine isolation that targets the quads directly with no fatigue anywhere else. | Q44: Set the pad on your lower shin and sit back into the seat | R44: Straighten your legs and pause briefly at the top | S44: Lower under control without letting the weight slam | T44: Swinging the weight up with momentum from the hips. | U44: Sissy Squat, Reverse Nordic Curl, Leg Press, Bodyweight Squat, Wall Sit | V44: 5 | W44: 0 | X44: Safe to train close to failure. Stop on sharp or joint pain and swap to Sissy Squat. | Y44: QD14, QD10, QD05, QD09, QD12 | Z44: Yes | AA44: No | AB44: machine_leg_extension | AD44: Low | AE44: Yes | AF44: Yes | AH44: weight_reps | AI44: kg | AJ44: knee
A45: QD08 | B45: Step Up | C45: Quads | D45: Quadriceps, glutes | E45: Lunge | F45: Quads | Lunge | G45: Compound | H45: Bodyweight | I45: Bench or box, optional dumbbells | J45: Beginner | K45: Yes | L45: Yes | M45: Load | N45: General Fitness | O45: Low skill, low impact and highly transferable to stairs and daily life. A safe entry point to single leg training for deconditioned users. | P45: A step up that builds single leg strength and carries straight over to stairs and sport. | Q45: Place one foot fully on a box around knee height | R45: Drive through that heel to stand up tall | S45: Lower slowly under control with the same leg | T45: Pushing off the back foot instead of driving with the top leg. | U45: Split Squat, Walking Lunge, Bulgarian Split Squat, Bodyweight Squat | V45: 4 | W45: 1 | X45: Free weight compound. Always stop at least one rep short of failure. Swap to Split Squat if form breaks down. | Y45: QD11, QD04, QD03, QD09 | Z45: No | AA45: No | AB45: bench/box/step | AC45: dumbbell | AD45: Low | AE45: No | AF45: Yes | AH45: weight_reps | AI45: kg | AJ45: knee, hip, ankle
A46: QD09 | B46: Bodyweight Squat | C46: Quads | D46: Quadriceps, glutes | E46: Squat | F46: Quads | Squat | G46: Compound | H46: Bodyweight | I46: None | J46: Beginner | K46: No | L46: No | M46: Rep | N46: General Fitness | O46: The squat pattern was entirely absent from the bodyweight tier. This restores it, teaches the movement before load is added, and needs nothing but floor space. | P46: The base squat pattern. Trains the legs and grooves the movement before you add load. | Q46: Stand with feet shoulder width, toes slightly out | R46: Sit down between your hips as far as you comfortably can | S46: Stand back up and squeeze your glutes | T46: Cutting the depth short and only using the top half of the range. | U46: Goblet Squat, Split Squat, Wall Sit, Leg Press, Step Up | V46: 5 | W46: 0 | X46: Safe to train close to failure. Stop on sharp or joint pain and swap to Goblet Squat. | Y46: QD02, QD11, QD12, QD05, QD08 | Z46: Yes | AA46: No | AB46: none | AD46: Low | AE46: No | AF46: Yes | AH46: reps | AI46: bodyweight | AJ46: knee, hip, lower_back
A47: QD10 | B47: Reverse Nordic Curl | C47: Quads | D47: Quadriceps, rectus femoris | E47: Isolation | F47: Quads | Knee Extension | G47: Isolation | H47: Bodyweight | I47: None | J47: Intermediate | K47: No | L47: No | M47: Rep | N47: Hypertrophy | O47: Loaded quad stretch with no equipment, and the only alternative to the leg extension machine. Removes a hard dependency on a single piece of gym kit. | P47: A brutal bodyweight quad isolation that also protects the knees over time. | Q47: Kneel tall on a soft surface with your glutes squeezed | R47: Lean back slowly, keeping a straight line from knees to head | S47: Go only as far as you can control, then pull yourself back up | T47: Breaking at the hips instead of staying in one straight line. | U47: Sissy Squat, Leg Extension, Wall Sit, Bodyweight Squat | V47: 4 | W47: 0 | X47: Safe to train close to failure. Stop on sharp or joint pain and swap to Sissy Squat. | Y47: QD14, QD07, QD12, QD09 | Z47: Yes | AA47: No | AB47: none | AD47: Low | AE47: Yes | AF47: Yes | AH47: reps | AI47: bodyweight | AJ47: knee
A48: QD11 | B48: Split Squat | C48: Quads | D48: Quadriceps, glutes | E48: Lunge | F48: Quads | Lunge | G48: Compound | H48: Bodyweight | I48: None | J48: Beginner | K48: Yes | L48: Yes | M48: Load | N48: General Fitness | O48: Stationary, so it needs no room to travel and no balance to walk. The safest single leg entry point and the regression the Bulgarian split squat was missing. | P48: A stationary lunge. All the single leg benefit with none of the balance drama. | Q48: Take a long stride and stay in that split stance | R48: Lower your back knee toward the floor | S48: Push through your front foot to stand back up | T48: Leaning the torso forward over the front knee. | U48: Walking Lunge, Step Up, Bulgarian Split Squat, Bodyweight Squat | V48: 4 | W48: 0 | X48: Safe to train close to failure. Stop on sharp or joint pain and swap to Walking Lunge. | Y48: QD04, QD08, QD03, QD09 | Z48: Yes | AA48: No | AB48: none | AD48: Low | AE48: No | AF48: Yes | AH48: weight_reps | AI48: kg | AJ48: knee, hip, ankle
A49: QD12 | B49: Wall Sit | C49: Quads | D49: Quadriceps | E49: Squat | F49: Quads | Squat | G49: Isolation | H49: Bodyweight | I49: Wall | J49: Beginner | K49: No | L49: No | M49: Time | N49: General Fitness | O49: Isometric, silent and needs a wall. Ideal for a shared house or a gap between lectures, and progressed by time rather than load. | P49: A static hold that builds quad endurance with no equipment and no impact. | Q49: Slide down a wall until your knees are at 90 degrees | R49: Keep your back flat against the wall and your weight in your heels | S49: Hold for time and breathe normally | T49: Resting the hands on the thighs to take the load off. | U49: Bodyweight Squat, Goblet Squat, Leg Press, Split Squat | V49: 4 | W49: 0 | X49: Safe to train close to failure. Stop on sharp or joint pain and swap to Bodyweight Squat. | Y49: QD09, QD02, QD05, QD11 | Z49: Yes | AA49: No | AB49: wall | AD49: Low | AE49: Yes | AF49: Yes | AH49: duration | AI49: seconds | AJ49: knee, hip, lower_back
A50: QD13 | B50: Jump Squat | C50: Quads | D50: Quadriceps, glutes | E50: Squat | F50: Quads | Squat | G50: Compound | H50: Bodyweight | I50: None | J50: Intermediate | K50: No | L50: No | M50: Power | N50: Fat Loss | O50: Adds power and a conditioning stimulus to the squat pattern. Lets a short bodyweight session drive heart rate without abandoning lower body training. | P50: An explosive squat that trains power and burns a lot of energy fast. | Q50: Drop into a quarter squat with your arms back | R50: Jump as high as you can, driving the arms up | S50: Land softly, absorb it through the knees and hips, then reset | T50: Landing stiff legged with a loud, hard thud. | U50: Bodyweight Squat, Goblet Squat, Walking Lunge, Step Up | V50: 4 | W50: 2 | X50: Never taken to failure. End the set as soon as speed or landing quality drops. | Y50: QD09, QD02, QD04, QD08 | Z50: No | AA50: No | AB50: none | AD50: High | AE50: No | AF50: Yes | AH50: reps | AI50: bodyweight | AJ50: knee, hip, lower_back
A51: HG01 | B51: Romanian Deadlift | C51: Hamstrings & Glutes | D51: Hamstrings, glutes, erectors | E51: Hinge | F51: Hamstrings & Glutes | Hinge | G51: Compound | H51: Basic Gym | I51: Barbell or dumbbells | J51: Intermediate | K51: No | L51: Yes | M51: Load | N51: Hypertrophy | O51: The main hip hinge for hamstring length and strength. Teaches the hinge pattern that protects the back in everyday lifting. | P51: A hip hinge that stretches and strengthens the hamstrings and glutes. | Q51: Hold the bar at your hips with a soft knee bend | R51: Push your hips back and slide the bar down your thighs | S51: Stop when you feel a hamstring stretch, then drive your hips forward | T51: Bending the knees and turning it into a deadlift. | U51: Single Leg Romanian Deadlift, Cable Pull Through, Dumbbell Deadlift, Back Extension, Hip Thrust, Glute Bridge, Prone Superman | V51: 7 | W51: 1 | X51: Free weight compound. Always stop at least one rep short of failure. Swap to Single Leg Romanian Deadlift if form breaks down. | Y51: HG07, HG08, BK13, HG09, HG02, HG03, HG12 | Z51: No | AA51: No | AB51: barbell/dumbbell | AD51: Low | AE51: No | AF51: Yes | AH51: weight_reps | AI51: kg | AJ51: lower_back, hip, hamstring
A52: HG02 | B52: Hip Thrust | C52: Hamstrings & Glutes | D52: Gluteus maximus | E52: Hinge | F52: H&G | Glute Bridge | G52: Compound | H52: Basic Gym | I52: Barbell, bench | J52: Beginner | K52: No | L52: Yes | M52: Load | N52: Hypertrophy | O52: Peak glute tension at full hip extension, where squats and deadlifts are easiest. Directly addresses the most requested aesthetic goal on the platform. | P52: The best loaded glute exercise there is, with almost no strain on the lower back. | Q52: Sit with your upper back on a bench and the bar over your hips | R52: Drive through your heels and lift your hips until your torso is level | S52: Squeeze the glutes at the top, then lower under control | T52: Overarching the lower back at the top instead of squeezing the glutes. | U52: Glute Bridge, Single Leg Glute Bridge, Cable Pull Through, Romanian Deadlift, Back Extension | V52: 5 | W52: 1 | X52: Free weight compound. Always stop at least one rep short of failure. Swap to Glute Bridge if form breaks down. | Y52: HG03, HG11, HG08, HG01, HG09 | Z52: No | AA52: No | AB52: barbell,bench | AD52: Low | AE52: Yes | AF52: Yes | AH52: weight_reps | AI52: kg | AJ52: lower_back, hip, hamstring
A53: HG03 | B53: Glute Bridge | C53: Hamstrings & Glutes | D53: Gluteus maximus | E53: Hinge | F53: H&G | Glute Bridge | G53: Compound | H53: Bodyweight | I53: None | J53: Beginner | K53: No | L53: No | M53: Rep | N53: General Fitness | O53: Floor based, no equipment, and the natural regression from the hip thrust. Also a reliable warm up to wake up the glutes before squatting. | P53: A floor glute bridge. The simplest way to learn how to actually use your glutes. | Q53: Lie on your back with your knees bent and heels close to your hips | R53: Drive through your heels and lift your hips | S53: Squeeze at the top, then lower slowly | T53: Pushing the hips so high that the lower back takes over. | U53: Hip Thrust, Single Leg Glute Bridge, Cable Pull Through, Back Extension, Prone Superman | V53: 5 | W53: 0 | X53: Safe to train close to failure. Stop on sharp or joint pain and swap to Hip Thrust. | Y53: HG02, HG11, HG08, HG09, HG12 | Z53: Yes | AA53: No | AB53: none | AD53: Low | AE53: Yes | AF53: Yes | AH53: reps | AI53: bodyweight | AJ53: lower_back, hip, hamstring
A54: HG04 | B54: Seated Leg Curl | C54: Hamstrings & Glutes | D54: Hamstrings | E54: Isolation | F54: H&G | Knee Flexion | G54: Isolation | H54: Full Gym | I54: Leg curl machine | J54: Beginner | K54: No | L54: Yes | M54: Load | N54: Hypertrophy | O54: Trains knee flexion, which no hinge covers. Hamstrings have two jobs and a complete program must train both. | P54: A machine curl that trains the hamstrings in a stretched, safe position. | Q54: Set the pad above your ankles and the thigh pad snug | R54: Curl your heels down and under the seat | S54: Return slowly without letting the stack crash | T54: Letting the hips lift off the seat to get more range. | U54: Lying Leg Curl, Slider Hamstring Curl, Nordic Hamstring Curl, Romanian Deadlift, Single Leg Romanian Deadlift | V54: 5 | W54: 0 | X54: Safe to train close to failure. Stop on sharp or joint pain and swap to Lying Leg Curl. | Y54: HG05, HG14, HG06, HG01, HG07 | Z54: Yes | AA54: No | AB54: machine_leg_curl | AD54: Low | AE54: Yes | AF54: Yes | AH54: weight_reps | AI54: kg | AJ54: knee, hip
A55: HG05 | B55: Lying Leg Curl | C55: Hamstrings & Glutes | D55: Hamstrings | E55: Isolation | F55: H&G | Knee Flexion | G55: Isolation | H55: Full Gym | I55: Leg curl machine | J55: Beginner | K55: No | L55: Yes | M55: Load | N55: Hypertrophy | O55: Equipment dependent alternative to the seated curl so the program never fails just because one machine is occupied or absent. | P55: A machine curl that isolates the hamstrings lying face down. | Q55: Lie face down with the pad just above your heels | R55: Curl your heels toward your glutes | S55: Lower slowly until your legs are almost straight | T55: Jerking the hips up off the bench to finish the rep. | U55: Seated Leg Curl, Slider Hamstring Curl, Nordic Hamstring Curl, Romanian Deadlift | V55: 4 | W55: 0 | X55: Safe to train close to failure. Stop on sharp or joint pain and swap to Seated Leg Curl. | Y55: HG04, HG14, HG06, HG01 | Z55: Yes | AA55: No | AB55: machine_leg_curl | AD55: Low | AE55: Yes | AF55: Yes | AH55: weight_reps | AI55: kg | AJ55: knee, hip
A56: HG06 | B56: Nordic Hamstring Curl | C56: Hamstrings & Glutes | D56: Hamstrings | E56: Isolation | F56: H&G | Knee Flexion | G56: Isolation | H56: Bodyweight | I56: Partner or anchor | J56: Advanced | K56: No | L56: No | M56: Rep | N56: General Fitness | O56: The strongest evidence base of any single exercise for reducing hamstring strain injury. Valuable for the sport playing segment of the user base. | P56: The hardest bodyweight hamstring exercise. Builds serious resistance to hamstring strains. Advanced users only. | Q56: Kneel with your ankles anchored and squeeze your glutes | R56: Lower your body forward as slowly as you can, staying in a straight line | S56: Catch yourself with your hands and push back to the start | T56: Bending at the hips instead of holding one straight line. | U56: Slider Hamstring Curl, Lying Leg Curl, Seated Leg Curl, Single Leg Romanian Deadlift, Romanian Deadlift | V56: 5 | W56: 2 | X56: Advanced only. Never taken to failure. Beginner and intermediate users are served Slider Hamstring Curl instead. | Y56: HG14, HG05, HG04, HG07, HG01 | Z56: No | AA56: No | AB56: partner/anchor_point | AD56: Low | AE56: No | AF56: Yes | AH56: reps | AI56: bodyweight | AJ56: knee, hip
A57: HG07 | B57: Single Leg Romanian Deadlift | C57: Hamstrings & Glutes | D57: Hamstrings, glutes | E57: Hinge | F57: Hamstrings & Glutes | Hinge | G57: Compound | H57: Bodyweight | I57: Optional dumbbell | J57: Intermediate | K57: Yes | L57: Yes | M57: Load | N57: General Fitness | O57: Combines hinge, balance and hip stability. Delivers a real hamstring stimulus from very light loads, which suits minimal home setups. | P57: A single leg hinge that builds hamstrings, glutes and balance with light load. | Q57: Stand on one leg with a soft knee bend | R57: Hinge forward, letting the back leg rise behind you | S57: Stop when your torso is level, then return to standing | T57: Letting the hips open out to the side instead of staying square. | U57: Romanian Deadlift, Cable Pull Through, Back Extension, Single Leg Glute Bridge, Prone Superman | V57: 5 | W57: 1 | X57: Free weight compound. Always stop at least one rep short of failure. Swap to Romanian Deadlift if form breaks down. | Y57: HG01, HG08, HG09, HG11, HG12 | Z57: No | AA57: No | AB57: none | AC57: dumbbell | AD57: Low | AE57: No | AF57: Yes | AH57: weight_reps | AI57: kg | AJ57: lower_back, hip, hamstring
A58: HG08 | B58: Cable Pull Through | C58: Hamstrings & Glutes | D58: Glutes, hamstrings | E58: Hinge | F58: Hamstrings & Glutes | Hinge | G58: Compound | H58: Full Gym | I58: Cable machine, rope | J58: Beginner | K58: No | L58: Yes | M58: Load | N58: General Fitness | O58: Teaches the hinge with the load pulling the hips backward, so the pattern clicks fast. Low spinal load makes it a good high rep finisher. | P58: A cable hinge that teaches the hip pattern with the load pulling you backwards, not down. | Q58: Face away from a low pulley with the rope between your legs | R58: Push your hips back until you feel a hamstring stretch | S58: Snap your hips forward and squeeze the glutes | T58: Pulling the rope with the arms instead of driving the hips. | U58: Romanian Deadlift, Hip Thrust, Glute Bridge, Back Extension, Prone Superman | V58: 5 | W58: 0 | X58: Safe to train close to failure. Stop on sharp or joint pain and swap to Romanian Deadlift. | Y58: HG01, HG02, HG03, HG09, HG12 | Z58: Yes | AA58: No | AB58: cable_machine,rope_attachment | AD58: Low | AE58: No | AF58: Yes | AH58: weight_reps | AI58: kg | AJ58: lower_back, hip, hamstring
A59: HG09 | B59: Back Extension | C59: Hamstrings & Glutes | D59: Erectors, glutes, hamstrings | E59: Hinge | F59: Hamstrings & Glutes | Hinge | G59: Isolation | H59: Basic Gym | I59: 45 degree bench or GHD | J59: Beginner | K59: No | L59: Yes | M59: Load | N59: General Fitness | O59: Builds lower back endurance, which is the actual weak link for students who sit and study all day. Low load, high return. | P59: A back extension that strengthens the hamstrings, glutes and spinal erectors together. | Q59: Set the pad just below your hip bones | R59: Hinge down until you feel a hamstring stretch | S59: Squeeze your glutes to raise your torso back to level | T59: Cranking past level into a big lower back arch. | U59: Prone Superman, Romanian Deadlift, Cable Pull Through, Glute Bridge | V59: 4 | W59: 0 | X59: Safe to train close to failure. Stop on sharp or joint pain and swap to Prone Superman. | Y59: HG12, HG01, HG08, HG03 | Z59: Yes | AA59: No | AB59: back_extension_bench | AD59: Low | AE59: Yes | AF59: Yes | AH59: weight_reps | AI59: kg | AJ59: lower_back, hip, hamstring
A60: HG10 | B60: Hip Abduction | C60: Hamstrings & Glutes | D60: Gluteus medius, gluteus minimus | E60: Isolation | F60: H&G | Abduction | G60: Isolation | H60: Bodyweight | I60: Resistance band or machine | J60: Beginner | K60: No | L60: Yes | M60: Load | N60: General Fitness | O60: The only movement here that trains hip abduction. Squats, hinges and lunges barely touch the glute medius, which drives knee tracking and lateral hip stability. Fills the largest coverage gap in the lower body. | P60: A hip abduction that strengthens the side glutes and helps stubborn knee and hip pain. | Q60: Sit or stand with a band or the machine pad at your knees | R60: Push your knees apart against the resistance | S60: Return slowly without letting the band snap back | T60: Leaning the torso back to force the range further. | U60: Lateral Band Walk, Single Leg Glute Bridge, Glute Bridge, Side Plank | V60: 4 | W60: 0 | X60: Safe to train close to failure. Stop on sharp or joint pain and swap to Lateral Band Walk. | Y60: HG13, HG11, HG03, CO07 | Z60: Yes | AA60: No | AB60: band/machine_abduction | AD60: Low | AE60: Yes | AF60: Yes | AH60: weight_reps | AI60: kg | AJ60: knee, hip
A61: HG11 | B61: Single Leg Glute Bridge | C61: Hamstrings & Glutes | D61: Gluteus maximus, hamstrings | E61: Hinge | F61: H&G | Glute Bridge | G61: Compound | H61: Bodyweight | I61: None | J61: Beginner | K61: Yes | L61: No | M61: Rep | N61: General Fitness | O61: Doubles the load on the glute bridge using bodyweight alone. Gives the bridge a progression so a bodyweight user is not stuck once it becomes easy. | P61: A one leg glute bridge that doubles the load on each glute with no equipment. | Q61: Lie on your back and lift one foot off the floor | R61: Drive through the planted heel and lift your hips | S61: Squeeze at the top and lower slowly | T61: Letting one hip drop lower than the other. | U61: Glute Bridge, Hip Thrust, Cable Pull Through, Back Extension | V61: 4 | W61: 0 | X61: Safe to train close to failure. Stop on sharp or joint pain and swap to Glute Bridge. | Y61: HG03, HG02, HG08, HG09 | Z61: Yes | AA61: No | AB61: none | AD61: Low | AE61: Yes | AF61: Yes | AH61: reps | AI61: bodyweight | AJ61: lower_back, hip, hamstring
A62: HG12 | B62: Prone Superman | C62: Hamstrings & Glutes | D62: Erectors, glutes | E62: Hinge | F62: Hamstrings & Glutes | Hinge | G62: Isolation | H62: Bodyweight | I62: None | J62: Beginner | K62: No | L62: No | M62: Rep | N62: General Fitness | O62: Lower back endurance from the floor, with no bench required. The bodyweight stand in for the back extension and safe for users with sensitive spines. | P62: A floor extension for the glutes and lower back. Ideal when you have nothing at all. | Q62: Lie face down with your arms out in front | R62: Lift your chest, arms and legs off the floor at once | S62: Hold briefly, then lower slowly | T62: Throwing the head back and straining the neck. | U62: Back Extension, Glute Bridge, Single Leg Glute Bridge, Romanian Deadlift | V62: 4 | W62: 0 | X62: Safe to train close to failure. Stop on sharp or joint pain and swap to Back Extension. | Y62: HG09, HG03, HG11, HG01 | Z62: Yes | AA62: No | AB62: none | AD62: Low | AE62: Yes | AF62: Yes | AH62: reps | AI62: bodyweight | AJ62: lower_back, hip, hamstring
A63: BI01 | B63: Barbell Curl | C63: Biceps | D63: Biceps brachii | E63: Isolation | F63: Biceps | Curl | G63: Isolation | H63: Basic Gym | I63: Barbell or EZ bar | J63: Beginner | K63: No | L63: Yes | M63: Load | N63: Hypertrophy | O63: The heaviest loadable curl, so it progresses cleanly. Standard reference movement for direct arm work. | P63: A loadable curl that lets you progress the biceps in small, trackable jumps. | Q63: Stand tall holding the bar with an underhand grip | R63: Curl the bar up without swinging your elbows forward | S63: Lower it slowly to straight arms | T63: Rocking the body back to swing the bar up. | U63: Cable Curl, Dumbbell Incline Curl, Hammer Curl, Band Curl, Chin Up (Close Grip), Supinated Inverted Row | V63: 6 | W63: 0 | X63: Safe to train close to failure. Stop on sharp or joint pain and swap to Cable Curl. | Y63: BI04, BI02, BI03, BI06, BI05, BI07 | Z63: Yes | AA63: No | AB63: barbell/ez_bar | AD63: Low | AE63: No | AF63: Yes | AH63: weight_reps | AI63: kg | AJ63: elbow
A64: BI02 | B64: Dumbbell Incline Curl | C64: Biceps | D64: Biceps brachii, long head | E64: Isolation | F64: Biceps | Curl | G64: Isolation | H64: Basic Gym | I64: Dumbbells, incline bench | J64: Intermediate | K64: Yes | L64: Yes | M64: Load | N64: Hypertrophy | O64: The shoulder extended position stretches the long head under load, which no standing curl achieves. Different stimulus, not just a different tool. | P64: A curl done lying back on an incline. Puts the biceps under a hard stretch. | Q64: Sit back on an incline bench and let your arms hang straight down | R64: Curl the dumbbells up without moving your elbows forward | S64: Lower all the way until your arms are fully straight | T64: Cutting the bottom of the rep short and losing the stretch. | U64: Barbell Curl, Cable Curl, Hammer Curl, Band Curl | V64: 4 | W64: 0 | X64: Safe to train close to failure. Stop on sharp or joint pain and swap to Barbell Curl. | Y64: BI01, BI04, BI03, BI06 | Z64: Yes | AA64: No | AB64: dumbbell,incline_bench | AD64: Low | AE64: Yes | AF64: Yes | AH64: weight_reps | AI64: kg | AJ64: elbow
A65: BI03 | B65: Hammer Curl | C65: Biceps | D65: Brachialis, brachioradialis | E65: Isolation | F65: Biceps | Curl | G65: Isolation | H65: Basic Gym | I65: Dumbbells | J65: Beginner | K65: Yes | L65: Yes | M65: Load | N65: Hypertrophy | O65: Trains the brachialis and forearm, which add arm thickness the supinated curl misses. Also gentler on cranky elbows and wrists. | P65: A neutral grip curl that builds the outer arm and forearm as well as the biceps. | Q65: Stand with dumbbells at your sides, palms facing in | R65: Curl up keeping the palms facing each other | S65: Lower slowly to straight arms | T65: Letting the elbows drift forward at the top. | U65: Barbell Curl, Cable Curl, Dumbbell Incline Curl, Band Curl | V65: 4 | W65: 0 | X65: Safe to train close to failure. Stop on sharp or joint pain and swap to Barbell Curl. | Y65: BI01, BI04, BI02, BI06 | Z65: Yes | AA65: No | AB65: dumbbell | AD65: Low | AE65: No | AF65: Yes | AH65: weight_reps | AI65: kg | AJ65: elbow
A66: BI04 | B66: Cable Curl | C66: Biceps | D66: Biceps brachii | E66: Isolation | F66: Biceps | Curl | G66: Isolation | H66: Full Gym | I66: Cable machine | J66: Beginner | K66: No | L66: Yes | M66: Load | N66: Hypertrophy | O66: Constant tension with no dead spot at the top. Good for high rep pump work at the end of a pull day. | P66: A cable curl that keeps tension on the biceps even at the top of the rep. | Q66: Stand a step back from a low pulley and grip the bar underhand | R66: Curl up with your elbows pinned to your sides | S66: Lower under control against the cable | T66: Stepping too close so the tension disappears at the bottom. | U66: Barbell Curl, Dumbbell Incline Curl, Hammer Curl, Band Curl | V66: 4 | W66: 0 | X66: Safe to train close to failure. Stop on sharp or joint pain and swap to Barbell Curl. | Y66: BI01, BI02, BI03, BI06 | Z66: Yes | AA66: No | AB66: cable_machine | AD66: Low | AE66: No | AF66: Yes | AH66: weight_reps | AI66: kg | AJ66: elbow
A67: BI05 | B67: Chin Up (Close Grip) | C67: Biceps | D67: Biceps brachii, lats | E67: Vertical Pull | F67: Biceps | Compound Pull | G67: Compound | H67: Bodyweight | I67: Pull up bar | J67: Advanced | K67: No | L67: Yes | M67: Load | N67: Strength | O67: The only heavy compound biceps option. Lets a time poor user train back and arms in one movement. | P67: A close grip chin up. The heaviest biceps exercise you can do. Advanced users only. | Q67: Hang from the bar with palms facing you, hands close together | R67: Pull your chest to the bar and think about curling yourself up | S67: Lower slowly to straight arms | T67: Swinging the legs to generate momentum. | U67: Supinated Inverted Row, Band Assisted Chin Up, Barbell Curl, Cable Curl, Hammer Curl | V67: 5 | W67: 2 | X67: Advanced only. Never taken to failure. Beginner and intermediate users are served Supinated Inverted Row instead. | Y67: BI07, BK15, BI01, BI04, BI03 | Z67: No | AA67: No | AB67: pull_up_bar | AD67: Low | AE67: No | AF67: Yes | AH67: weight_reps | AI67: kg | AJ67: shoulder, elbow
A68: BI06 | B68: Band Curl | C68: Biceps | D68: Biceps brachii | E68: Isolation | F68: Biceps | Curl | G68: Isolation | H68: Bodyweight | I68: Resistance band | J68: Beginner | K68: Yes | L68: Yes | M68: Load | N68: General Fitness | O68: A bodyweight beginner previously had no biceps option, since the chin up is advanced. Bands give a scalable curl anywhere. | P68: A banded curl for training the arms with no weights at all. | Q68: Stand on the band and hold the ends with palms up | R68: Curl your hands to your shoulders | S68: Lower slowly and fight the band on the way down | T68: Letting the band snap the arms back down. | U68: Hammer Curl, Barbell Curl, Cable Curl, Supinated Inverted Row | V68: 4 | W68: 0 | X68: Safe to train close to failure. Stop on sharp or joint pain and swap to Hammer Curl. | Y68: BI03, BI01, BI04, BI07 | Z68: Yes | AA68: No | AB68: band | AD68: Low | AE68: No | AF68: Yes | AH68: weight_reps | AI68: kg | AJ68: elbow
A69: BI07 | B69: Supinated Inverted Row | C69: Biceps | D69: Biceps brachii, lats | E69: Horizontal Pull | F69: Biceps | Compound Pull | G69: Compound | H69: Bodyweight | I69: Bar, rings or table edge | J69: Beginner | K69: No | L69: No | M69: Rep | N69: General Fitness | O69: A beginner friendly compound biceps option, since the chin up is advanced and the band curl was the only other choice. Difficulty scales purely by foot position. | P69: An underhand bodyweight row that loads the biceps and back at the same time. | Q69: Lie under a bar and grip it underhand, shoulder width | R69: Pull your chest to the bar, elbows close to your body | S69: Lower until your arms are straight | T69: Letting the hips sag instead of holding a rigid line. | U69: Band Assisted Chin Up, Chin Up (Close Grip), Band Curl, Hammer Curl, Barbell Curl | V69: 5 | W69: 0 | X69: Safe to train close to failure. Stop on sharp or joint pain and swap to Band Assisted Chin Up. | Y69: BK15, BI05, BI06, BI03, BI01 | Z69: Yes | AA69: No | AB69: low_bar/rings/sturdy_table | AD69: Low | AE69: No | AF69: Yes | AH69: reps | AI69: bodyweight | AJ69: shoulder, elbow, upper_back
... A111: HG14 | B111: Slider Hamstring Curl | C111: Hamstrings & Glutes | D111: Hamstrings, glutes | E111: Isolation | F111: H&G | Knee Flexion | G111: Isolation | H111: Bodyweight | I111: Sliders, towel or socks | J111: Beginner | K111: No | L111: No | M111: Rep | N111: General Fitness | O111: A scalable knee flexion exercise for users with no leg curl machine. Sits between the glute bridge and the Nordic curl in difficulty. | P111: A hamstring curl using sliders, towels or socks. Real hamstring work with no machine. | Q111: Lie on your back with your heels on sliders and hips lifted | R111: Slide your heels out until your legs are almost straight | S111: Pull them back in without letting your hips drop | T111: Letting the hips sag as the legs extend. | U111: Lying Leg Curl, Seated Leg Curl, Nordic Hamstring Curl, Single Leg Glute Bridge | V111: 4 | W111: 0 | X111: Safe to train close to failure. Stop on sharp or joint pain and swap to Lying Leg Curl. | Y111: HG05, HG04, HG06, HG11 | Z111: Yes | AA111: No | AB111: sliders/towel/smooth_floor | AD111: Low | AE111: Yes | AF111: Yes | AH111: reps | AI111: bodyweight | AJ111: knee, hip
A112: CO14 | B112: Russian Twist | C112: Core | D112: Obliques, rectus abdominis | E112: Rotation | F112: Core | Rotation | G112: Isolation | H112: Bodyweight | I112: Optional dumbbell or plate | J112: Beginner | K112: No | L112: Yes | M112: Rep | N112: General Fitness | O112: The only equipment free rotation exercise in the database. Gives the bodyweight tier a like for like swap for the cable woodchop. | P112: A seated twist that trains the obliques with no equipment needed. | Q112: Sit with your knees bent and lean your torso back slightly | R112: Rotate your ribs to one side, then the other | S112: Keep your chest tall and move slowly | T112: Whipping side to side with the arms while the torso stays fixed. | U112: Standing Band Rotation, Cable Woodchop, Side Plank, Pallof Press | V112: 4 | W112: 0 | X112: Safe to train close to failure. Stop on sharp or joint pain and swap to Standing Band Rotation. | Y112: CO10, CO04, CO07, CO05 | Z112: Yes | AA112: No | AB112: none | AC112: dumbbell/plate | AD112: Low | AE112: Yes | AF112: Yes | AH112: weight_reps | AI112: kg | AJ112: lower_back, core
A113: FB10 | B113: High Knees | C113: Full Body & Conditioning | D113: Hip flexors, calves, core | E113: Conditioning | F113: Full Body & Conditioning | Conditioning | G113: Compound | H113: Bodyweight | I113: None | J113: Beginner | K113: No | L113: No | M113: Interval | N113: Fat Loss | O113: Conditioning that needs a square metre of floor and nothing else. Backs up the jumping jack so no conditioning slot is ever left without a swap. | P113: A running drill on the spot. Simple conditioning that needs no space or gear. | Q113: Stand tall and run on the spot | R113: Drive each knee up toward hip height | S113: Stay on the balls of your feet and pump your arms | T113: Barely lifting the knees and just jogging on the spot. | U113: Jumping Jack, Mountain Climber, Bear Crawl, Burpee | V113: 4 | W113: 0 | X113: Safe to train close to failure. Stop on sharp or joint pain and swap to Jumping Jack. | Y113: FB08, FB04, FB09, FB03 | Z113: Yes | AA113: No | AB113: none | AD113: High | AE113: No | AF113: Yes | AH113: interval | AI113: rounds | AJ113: knee, ankle, hip
A114: FB11 | B114: Dumbbell Swing | C114: Full Body & Conditioning | D114: Glutes, hamstrings, erector spinae, delts | E114: Hinge | F114: Full Body & Conditioning | Hinge | G114: Compound | H114: Basic Gym | I114: Single dumbbell | J114: Beginner | K114: No | L114: Yes | M114: Power | N114: Fat Loss | O114: A like for like swap for the kettlebell swing in gyms with no kettlebells, which is most university gyms. | P114: A dumbbell swing. All the power and conditioning of a kettlebell swing without the kettlebell. | Q114: Hold one dumbbell by the head with both hands | R114: Hinge and hike it back between your legs | S114: Snap your hips forward and let it swing to chest height | T114: Lifting with the shoulders instead of driving the hips. | U114: Kettlebell Swing, Cable Pull Through, Romanian Deadlift, Jump Squat, Jumping Jack | V114: 5 | W114: 2 | X114: Never taken to failure. End the set as soon as speed or landing quality drops. | Y114: FB01, HG08, HG01, QD13, FB08 | Z114: No | AA114: No | AB114: dumbbell | AD114: Moderate | AE114: No | AF114: Yes | AH114: reps | AI114: bodyweight | AJ114: lower_back, hip, hamstring
A115: FB12 | B115: Treadmill Interval | C115: Full Body & Conditioning | D115: Legs, cardiovascular system | E115: Conditioning | F115: Full Body & Conditioning | Conditioning | G115: Compound | H115: Full Gym | I115: Treadmill | J115: Beginner | K115: No | L115: No | M115: Interval | N115: Fat Loss | O115: The most familiar piece of cardio equipment in any gym. Low skill, low impact when walked, scalable to running for fitter users. | P115: Walk or run intervals on a treadmill to raise your heart rate and build a base of fitness. | Q115: Warm up at an easy walk for 2 to 3 minutes | R115: Push the pace or incline for the work interval, then ease back to recover | S115: Repeat the work and recover pattern for the set time, then cool down | T115: Holding the rails, which takes the work out of it and wrecks your posture. | U115: Stationary Bike Interval, Stairmaster Interval, Rowing Machine Interval, High Knees, Jumping Jack | V115: 5 | W115: 4 | X115: Low impact when walked. Progress to running only when comfortable. Stop on any chest pain, dizziness or unusual breathlessness (S06). | Y115: FB06, FB13, FB05, FB10, FB08 | Z115: Yes | AA115: No | AB115: treadmill | AD115: Moderate | AE115: No | AF115: Yes | AH115: interval | AI115: rounds | AJ115: knee, ankle, hip
A116: FB13 | B116: Stairmaster Interval | C116: Full Body & Conditioning | D116: Legs, glutes, cardiovascular system | E116: Conditioning | F116: Full Body & Conditioning | Conditioning | G116: Compound | H116: Full Gym | I116: Stair climber machine | J116: Beginner | K116: No | L116: No | M116: Interval | N116: Fat Loss | O116: Hard cardio that also loads the glutes and quads, with far less joint impact than running. A gym staple. | P116: Climb a moving staircase at a steady or interval pace to build fitness and leg endurance. | Q116: Start at an easy pace and stand tall, weight through your whole foot | R116: Raise the level for the work interval, then drop it back to recover | S116: Keep an upright posture the whole time and repeat for the set duration | T116: Leaning your bodyweight onto the handrails so your legs barely work. | U116: Treadmill Interval, Stationary Bike Interval, Rowing Machine Interval, High Knees, Walking Lunge | V116: 5 | W116: 4 | X116: Low impact but demanding. Keep an upright posture and do not hang on the rails. Stop on chest pain, dizziness or breathlessness (S06). | Y116: FB12, FB06, FB05, FB10, QD04 | Z116: Yes | AA116: No | AB116: stairmaster | AD116: Low | AE116: No | AF116: Yes | AH116: interval | AI116: rounds | AJ116: knee, hip, ankle
A117: FB14 | B117: Stationary Bike Steady | C117: Full Body & Conditioning | D117: Legs, cardiovascular system | E117: Conditioning | F117: Full Body & Conditioning | Conditioning | G117: Compound | H117: Full Gym | I117: Stationary bike | J117: Beginner | K117: No | L117: No | M117: Interval | N117: Fat Loss | O117: The lowest impact and lowest skill cardio there is. Ideal for recovery days, deloads, exam-period minimal movement, and anyone with knee or ankle limits. | P117: A steady, low impact ride to build aerobic fitness or keep moving on an easy day. | Q117: Set the seat so your knee stays slightly bent at the bottom of the pedal stroke | R117: Ride at a conversational pace you could hold for the whole session | S117: Keep a smooth, even cadence and relax your upper body | T117: Setting the seat too low, which cramps the knees over a long ride. | U117: Stationary Bike Interval, Treadmill Interval, Rowing Machine Interval, Stairmaster Interval | V117: 4 | W117: 4 | X117: The gentlest cardio option, safe for most limitations. Still stop on chest pain, dizziness or breathlessness (S06). | Y117: FB06, FB12, FB05, FB13 | Z117: Yes | AA117: No | AB117: stationary_bike | AD117: Low | AE117: No | AF117: Yes | AH117: interval | AI117: rounds | AJ117: knee

Sheet Substitutions
A1: Substitutions
A2: Normalized substitution collection. One row per pair, ID based so renames never break it. Key = exercise_id-substitute_id, use as the Firestore document ID. Priority 1 is the best swap. The generator walks priority order and returns the FIRST substitute compatible with the user's skill level, equipment, restrictions and exclusion history. It never assumes priority 1 is valid.
A4: key | B4: exercise_id | C4: substitute_id | D4: priority | E4: match_type
A5: CH01-CH02 | B5: CH01 | C5: CH02 | D5: 1 | E5: like_for_like
A6: CH01-CH05 | B6: CH01 | C6: CH05 | D6: 2 | E6: like_for_like
A7: CH01-CH09 | B7: CH01 | C7: CH09 | D7: 3 | E7: like_for_like
A8: CH01-CH03 | B8: CH01 | C8: CH03 | D8: 4 | E8: like_for_like
A9: CH01-TR01 | B9: CH01 | C9: TR01 | D9: 5 | E9: same_muscle_group
A10: CH01-CH10 | B10: CH01 | C10: CH10 | D10: 6 | E10: like_for_like
A11: CH01-CH12 | B11: CH01 | C11: CH12 | D11: 7 | E11: like_for_like
A12: CH01-CH04 | B12: CH01 | C12: CH04 | D12: 8 | E12: like_for_like
A13: CH01-CH11 | B13: CH01 | C13: CH11 | D13: 9 | E13: like_for_like
A14: CH01-CH07 | B14: CH01 | C14: CH07 | D14: 10 | E14: same_muscle_group
A15: CH02-CH05 | B15: CH02 | C15: CH05 | D15: 1 | E15: like_for_like
A16: CH02-CH01 | B16: CH02 | C16: CH01 | D16: 2 | E16: like_for_like
... A546: FB14-FB13 | B546: FB14 | C546: FB13 | D546: 4 | E546: like_for_like

Sheet Exercise Swaps
A1: Exercise Swaps (runtime)
A2: How the coach AI handles a mid-program request to change an exercise. Every swap is resolved by walking the Substitutions sheet in priority order and returning the FIRST entry that passes the user's equipment, skill and exclusion filters, never by inventing an exercise. A swap changes which exercise fills a slot, never the slot's safety envelope: the new exercise is re-prescribed from Prescription Logic and re-clamped by Safety Rules and its own Min RIR. Every swap writes to swap_history; dislike and pain swaps also update excluded_exercise_ids. A reported stop symptom is never a swap, it is an S06 escalation.
A4: swap_id | B4: trigger | C4: how_the_user_signals_it | D4: coach_action | E4: reason_code | F4: persistence
A5: SW01 | B5: user dislikes the exercise | C5: User taps swap or tells the coach they dislike it | D5: Walk the Substitutions list for that exercise in priority order. Return the first entry that passes the user's equipment tags, skill level and exclusions. Serve it in the same slot with the same slot prescription. | E5: dislike | F5: Permanent. Add from_id to excluded_exercise_ids so it is never served again unless the user re-enables it.
A6: SW02 | B6: exercise hurts (non-acute) | C6: User says it is uncomfortable or aggravates a known area, but reports no stop symptom | D6: Same as SW01, and additionally skip any substitute whose Stress Regions overlap the user's affected_regions, and any sharing the flagged movement pattern. Prefer Supported=Yes and Impact=Low substitutes. Region matching is now structured (Exercise Database Stress Regions vs users.affected_regions), not inferred from names. At program-build time this is driven by the Injury Modifications sheet; mid-program pain swaps use the same region rows. | E6: pain | F6: Permanent block on from_id pending user confirmation the area is fine. Logs a pain_flag.
A7: SW03 | B7: stop symptom during exercise | C7: User reports chest pain, dizziness, faintness, unusual breathlessness, palpitations, numbness or sharp joint pain | D7: Do NOT swap and continue. Trigger Safety Rule S06: end the session, show the stop message, halt further generation until resolved or cleared. This overrides any swap request. | E7: stop_symptom | F7: Escalation, not a swap. Writes a stop_symptom_event to flags.
A8: SW04 | B8: equipment unavailable | C8: Chosen exercise needs a machine or tool the user cannot access right now | D8: Walk Substitutions for the first entry whose required_equipment_tags are a subset of the user's available tags. Temporary swaps (busy gym) are not added to exclusions. | E8: equipment | F8: Session-only unless the user changes their stored equipment, then permanent for the program.
A9: SW05 | B9: too hard | C9: User cannot complete the prescribed reps with acceptable form, or reports the movement is beyond them | D9: First reduce load or reps within the slot (see Progression Engine down-adjust). If the exercise itself is the problem, walk Substitutions to the first entry at or below the user's skill level and, for compounds, prefer a more supported or machine variation. | E9: skill | F9: Temporary. Re-offers the original once progression_state shows the user has advanced.
A10: SW06 | B10: too easy | C10: User finds it trivial even at target load and top of the rep range | D10: First progress load or reps (see Progression Engine up-adjust). Only swap the exercise if the user specifically wants variety, in which case offer a same-group substitute of equal or higher skill. | E10: preference | F10: No exclusion. Variety swap only.
A11: SW07 | B11: wants a specific exercise | C11: User names an exercise they want in a slot | D11: If the named exercise exists in the database, passes their equipment and skill filters, and fits the slot's muscle_group and type filters, place it. If it fails a HARD_SAFETY rule or the slot filter, explain why in one sentence and offer the closest valid option. | E11: user_choice | F11: Honoured where safe. Never overrides screening, skill gates or equipment reality.
A12: SW08 | B12: wants variety generally | C12: User is bored, no specific target | D12: Rotate one or two slots to same-group substitutes the user has not done recently, keeping the day's muscle and volume targets intact. | E12: preference | F12: No exclusion. Freshness tracked so the same swaps are not repeated.

Sheet Summary
A1: Coverage Check
A2: Live counts driven off the Exercise Database sheet. Use this to spot gaps before shipping the program generator.
A4: By Muscle Group
A5: Category | B5: Count | C5: % of DB
A6: Chest | B6: =COUNTIF('Exercise Database'!$C$5:$C$117,$A6) -> 12 | C6: =IF($B$16=0,0,B6/$B$16) -> 0.10619469
A7: Back | B7: =COUNTIF('Exercise Database'!$C$5:$C$117,$A7) -> 15 | C7: =IF($B$16=0,0,B7/$B$16) -> 0.13274336
A8: Shoulders | B8: =COUNTIF('Exercise Database'!$C$5:$C$117,$A8) -> 12 | C8: =IF($B$16=0,0,B8/$B$16) -> 0.10619469
A9: Quads | B9: =COUNTIF('Exercise Database'!$C$5:$C$117,$A9) -> 14 | C9: =IF($B$16=0,0,B9/$B$16) -> 0.12389381
A10: Hamstrings & Glutes | B10: =COUNTIF('Exercise Database'!$C$5:$C$117,$A10) -> 14 | C10: =IF($B$16=0,0,B10/$B$16) -> 0.12389381
A11: Biceps | B11: =COUNTIF('Exercise Database'!$C$5:$C$117,$A11) -> 7 | C11: =IF($B$16=0,0,B11/$B$16) -> 0.061946903
A12: Triceps | B12: =COUNTIF('Exercise Database'!$C$5:$C$117,$A12) -> 7 | C12: =IF($B$16=0,0,B12/$B$16) -> 0.061946903
A13: Core | B13: =COUNTIF('Exercise Database'!$C$5:$C$117,$A13) -> 14 | C13: =IF($B$16=0,0,B13/$B$16) -> 0.12389381
A14: Calves | B14: =COUNTIF('Exercise Database'!$C$5:$C$117,$A14) -> 4 | C14: =IF($B$16=0,0,B14/$B$16) -> 0.03539823
A15: Full Body & Conditioning | B15: =COUNTIF('Exercise Database'!$C$5:$C$117,$A15) -> 14 | C15: =IF($B$16=0,0,B15/$B$16) -> 0.12389381
A16: Total | B16: =SUM(B6:B15) -> 113 | C16: =IF(B16=0,0,SUM(C6:C15)) -> 1
A18: By Equipment Tier
A19: Category | B19: Count | C19: % of DB
A20: Bodyweight | B20: =COUNTIF('Exercise Database'!$H$5:$H$117,$A20) -> 52 | C20: =IF($B$23=0,0,B20/$B$23) -> 0.46017699
A21: Basic Gym | B21: =COUNTIF('Exercise Database'!$H$5:$H$117,$A21) -> 33 | C21: =IF($B$23=0,0,B21/$B$23) -> 0.2920354
A22: Full Gym | B22: =COUNTIF('Exercise Database'!$H$5:$H$117,$A22) -> 28 | C22: =IF($B$23=0,0,B22/$B$23) -> 0.24778761
A23: Total | B23: =SUM(B20:B22) -> 113 | C23: =IF(B23=0,0,SUM(C20:C22)) -> 1
A25: By Skill Level
A26: Category | B26: Count | C26: % of DB
A27: Beginner | B27: =COUNTIF('Exercise Database'!$J$5:$J$117,$A27) -> 77 | C27: =IF($B$30=0,0,B27/$B$30) -> 0.68141593
A28: Intermediate | B28: =COUNTIF('Exercise Database'!$J$5:$J$117,$A28) -> 27 | C28: =IF($B$30=0,0,B28/$B$30) -> 0.23893805
A29: Advanced | B29: =COUNTIF('Exercise Database'!$J$5:$J$117,$A29) -> 9 | C29: =IF($B$30=0,0,B29/$B$30) -> 0.079646018
A30: Total | B30: =SUM(B27:B29) -> 113 | C30: =IF(B30=0,0,SUM(C27:C29)) -> 1
A32: By Primary Goal Fit
A33: Category | B33: Count | C33: % of DB
A34: Strength | B34: =COUNTIF('Exercise Database'!$N$5:$N$117,$A34) -> 14 | C34: =IF($B$38=0,0,B34/$B$38) -> 0.12389381
A35: Hypertrophy | B35: =COUNTIF('Exercise Database'!$N$5:$N$117,$A35) -> 36 | C35: =IF($B$38=0,0,B35/$B$38) -> 0.31858407
A36: Fat Loss | B36: =COUNTIF('Exercise Database'!$N$5:$N$117,$A36) -> 14 | C36: =IF($B$38=0,0,B36/$B$38) -> 0.12389381
A37: General Fitness | B37: =COUNTIF('Exercise Database'!$N$5:$N$117,$A37) -> 49 | C37: =IF($B$38=0,0,B37/$B$38) -> 0.43362832
A38: Total | B38: =SUM(B34:B37) -> 113 | C38: =IF(B38=0,0,SUM(C34:C37)) -> 1
A40: By Type
A41: Category | B41: Count | C41: % of DB
A42: Compound | B42: =COUNTIF('Exercise Database'!$G$5:$G$117,$A42) -> 64 | C42: =IF($B$44=0,0,B42/$B$44) -> 0.56637168
A43: Isolation | B43: =COUNTIF('Exercise Database'!$G$5:$G$117,$A43) -> 49 | C43: =IF($B$44=0,0,B43/$B$44) -> 0.43362832
A44: Total | B44: =SUM(B42:B43) -> 113 | C44: =IF(B44=0,0,SUM(C42:C43)) -> 1
A46: By Prescription Class
A47: Category | B47: Count | C47: % of DB
A48: Load | B48: =COUNTIF('Exercise Database'!$M$5:$M$117,$A48) -> 65 | C48: =IF($B$53=0,0,B48/$B$53) -> 0.57522124
A49: Rep | B49: =COUNTIF('Exercise Database'!$M$5:$M$117,$A49) -> 26 | C49: =IF($B$53=0,0,B49/$B$53) -> 0.2300885
A50: Time | B50: =COUNTIF('Exercise Database'!$M$5:$M$117,$A50) -> 8 | C50: =IF($B$53=0,0,B50/$B$53) -> 0.07079646
A51: Interval | B51: =COUNTIF('Exercise Database'!$M$5:$M$117,$A51) -> 10 | C51: =IF($B$53=0,0,B51/$B$53) -> 0.088495575
A52: Power | B52: =COUNTIF('Exercise Database'!$M$5:$M$117,$A52) -> 4 | C52: =IF($B$53=0,0,B52/$B$53) -> 0.03539823
A53: Total | B53: =SUM(B48:B52) -> 113 | C53: =IF(B53=0,0,SUM(C48:C52)) -> 1
A55: Substitution Coverage
A56: Exercises in database | B56: =COUNTA('Exercise Database'!$A$5:$A$117) -> 113
A57: Exercises with at least 1 substitution | B57: =COUNTIF('Exercise Database'!$V$5:$V$117,">=1") -> 113
A58: Exercises with at least 3 substitutions | B58: =COUNTIF('Exercise Database'!$V$5:$V$117,">=3") -> 113
A59: Average substitutions per exercise | B59: =ROUND(AVERAGE('Exercise Database'!$V$5:$V$117),1) -> 4.8
A60: Exercises with no substitution | B60: =COUNTIF('Exercise Database'!$V$5:$V$117,0) -> 0

Sheet Substitution Matrix
A1: Swap Logic
A2: Every exercise has at least three prepared alternatives, listed best first. Tier 1 is a true like for like swap from the same substitution group. Tier 2 is a same muscle group swap, used when a user simply dislikes or cannot access the movement. Advanced lifts always list an easier swap first.
A4: ID | B4: Exercise | C4: Substitution Group | D4: Substitutions (Best First) | E4: Total | F4: Tier 1 | G4: Swap Note
A5: CH01 | B5: Barbell Bench Press | C5: Chest | Press | D5: Dumbbell Bench Press, Machine Chest Press, Incline Barbell Bench Press, Incline Dumbbell Press, Close Grip Bench Press, Decline Barbell Bench Press, Feet Elevated Push Up, Push Up, Incline Push Up, Dumbbell Chest Fly | E5: 10 | F5: 8 | G5: Multiple like for like swaps available.
A6: CH02 | B6: Dumbbell Bench Press | C6: Chest | Press | D6: Machine Chest Press, Barbell Bench Press, Incline Dumbbell Press, Feet Elevated Push Up, Push Up, Incline Push Up, Dumbbell Chest Fly, Cable Chest Fly | E6: 8 | F6: 6 | G6: Multiple like for like swaps available.
A7: CH03 | B7: Incline Dumbbell Press | C7: Chest | Press | D7: Incline Barbell Bench Press, Dumbbell Bench Press, Machine Chest Press, Barbell Bench Press, Feet Elevated Push Up, Push Up, Incline Push Up, Cable Chest Fly | E7: 8 | F7: 7 | G7: Multiple like for like swaps available.
A8: CH04 | B8: Push Up | C8: Chest | Press | D8: Incline Push Up, Feet Elevated Push Up, Machine Chest Press, Dumbbell Bench Press, Barbell Bench Press, Diamond Push Up, Dumbbell Chest Fly | E8: 7 | F8: 5 | G8: Multiple like for like swaps available.
A9: CH05 | B9: Machine Chest Press | C9: Chest | Press | D9: Dumbbell Bench Press, Barbell Bench Press, Incline Dumbbell Press, Push Up, Incline Push Up, Cable Chest Fly | E9: 6 | F9: 5 | G9: Multiple like for like swaps available.
A10: CH06 | B10: Cable Chest Fly | C10: Chest | Fly | D10: Dumbbell Chest Fly, Machine Chest Press, Dumbbell Bench Press, Push Up, Incline Push Up | E10: 5 | F10: 1 | G10: One like for like swap (Dumbbell Chest Fly). Rest are same muscle group.
A11: CH07 | B11: Dumbbell Chest Fly | C11: Chest | Fly | D11: Cable Chest Fly, Machine Chest Press, Dumbbell Bench Press, Push Up, Incline Push Up | E11: 5 | F11: 1 | G11: One like for like swap (Cable Chest Fly). Rest are same muscle group.
A12: CH08 | B12: Dip (Chest Lean) | C12: Chest | Press | D12: Feet Elevated Push Up, Dumbbell Bench Press, Machine Chest Press, Decline Barbell Bench Press, Push Up, Bench Dip, Incline Push Up | E12: 7 | F12: 6 | G12: Advanced only. Serve Feet Elevated Push Up to beginner and intermediate users.
A13: CH09 | B13: Incline Barbell Bench Press | C13: Chest | Press | D13: Incline Dumbbell Press, Barbell Bench Press, Dumbbell Bench Press, Machine Chest Press, Push Up, Incline Push Up | E13: 6 | F13: 6 | G13: Multiple like for like swaps available.
A14: CH10 | B14: Decline Barbell Bench Press | C14: Chest | Press | D14: Barbell Bench Press, Dumbbell Bench Press, Dip (Chest Lean), Machine Chest Press, Feet Elevated Push Up, Push Up | E14: 6 | F14: 6 | G14: Multiple like for like swaps available.
A15: CH11 | B15: Incline Push Up | C15: Chest | Press | D15: Push Up, Machine Chest Press, Dumbbell Bench Press, Feet Elevated Push Up, Dumbbell Chest Fly | E15: 5 | F15: 4 | G15: Multiple like for like swaps available.
A16: CH12 | B16: Feet Elevated Push Up | C16: Chest | Press | D16: Push Up, Incline Push Up, Dip (Chest Lean), Dumbbell Bench Press, Machine Chest Press | E16: 5 | F16: 5 | G16: Multiple like for like swaps available.
... A114: FB11 | B114: Dumbbell Swing | C114: Full Body & Conditioning | Hinge | D114: Kettlebell Swing, Cable Pull Through, Romanian Deadlift, Jump Squat | E114: 4 | F114: 1 | G114: One like for like swap (Kettlebell Swing). Rest are same muscle group.

Sheet Field Guide
A1: How The Program Generator Should Read Each Column
A3: Column | B3: What it does
A4: ID | B4: Stable primary key. Never reuse or renumber. Log sets against this, not the exercise name.
A5: Muscle Group | B5: Top level filter. Used to hit weekly volume targets per muscle.
A6: Movement Pattern | B6: Ensures a program covers push, pull, squat, hinge, lunge, carry and core rather than repeating one pattern.
A7: Type | B7: Compound movements are placed first in a session. Isolation movements fill remaining volume.
A8: Equipment Tier | B8: Hard filter set at onboarding. Bodyweight is a strict subset of Basic Gym, which is a strict subset of Full Gym.
A9: Skill Level | B9: Gate against user experience. A first time lifter is never served an Advanced movement in week one.
A10: Unilateral | B10: Flag for imbalance correction and for low equipment users who need more stimulus from light loads.
A11: Loadable | B11: If No, progress via reps, tempo or leverage instead of adding weight.
A12: Primary Goal Fit | B12: Weighting, not a hard filter. A hypertrophy user can still be given a Strength tagged lift.
A13: Why It Is In The Database | B13: Selection rationale. Each exercise earns its slot by covering something no other exercise covers.
A14: What It Does | B14: One line shown under the video on the exercise screen. Sells the exercise to the user in plain language.
... A53: Claude Code Notes sheet | B53: In-app engineering notes (editable training days, catch-up on misses, pulling activity into the generator, optional activity step, injury region mapping, free-text red-flag scan). Fold into the Build Backlog.

Sheet Prescription Logic
A1: Prescription Grid
A2: One row per Goal and Prescription Class. Key = Goal|Class, unique, use it as the Firestore document ID. Every number is a plain number, no text, no ranges inside a cell. Empty means not applicable. RIR is reps left in reserve. Higher RIR is easier and safer. Sets, reps, seconds and rest are all min and max pairs.
A4: key | B4: goal | C4: prescription_class | D4: sets_min | E4: sets_max | F4: reps_min | G4: reps_max | H4: duration_sec_min | I4: duration_sec_max | J4: rir_min | K4: rir_max | L4: rest_sec_min | M4: rest_sec_max | N4: pct_1rm_min | O4: pct_1rm_max | P4: rounds_min | Q4: rounds_max | R4: progression_rule | S4: coach_note
A5: Strength|Load | B5: Strength | C5: Load | D5: 3 | E5: 5 | F5: 4 | G5: 6 | J5: 1 | K5: 3 | L5: 180 | M5: 300 | N5: 75 | O5: 88 | R5: Add 2.5kg upper body or 5kg lower body once the top set hits reps_max in two sessions in a row. Never add more than 5 percent load in a week. | S5: Heavy load with long rest. Reps stay at 4 or above so the app never prescribes a near maximal single.
A6: Strength|Rep | B6: Strength | C6: Rep | D6: 4 | E6: 6 | F6: 4 | G6: 8 | J6: 1 | K6: 2 | L6: 150 | M6: 180 | R6: Move to a harder version of the exercise rather than adding reps. Once a set passes 8 reps, progress the variation. | S6: No load to add, so difficulty comes from leverage.
A7: Strength|Time | B7: Strength | C7: Time | D7: 3 | E7: 4 | H7: 20 | I7: 40 | J7: 2 | K7: 3 | L7: 120 | M7: 180 | R7: Add load first, seconds second. Hold time is capped at 40 seconds. | S7: Short heavy holds. Long holds become endurance work.
A8: Strength|Power | B8: Strength | C8: Power | D8: 3 | E8: 5 | F8: 3 | G8: 5 | J8: 3 | K8: 5 | L8: 120 | M8: 180 | R8: Add height, distance or load only while movement speed stays the same. Stop the set the moment speed drops. | S8: Never taken near failure. A failed power rep is a fall.
A9: Strength|Interval | B9: Strength | C9: Interval | D9: 1 | E9: 1 | H9: 480 | I9: 720 | J9: 4 | K9: 6 | R9: Do not progress. Keep it as an easy warm up only. | S9: Conditioning competes with heavy lifting recovery, so keep it small.
A10: Hypertrophy|Load | B10: Hypertrophy | C10: Load | D10: 3 | E10: 4 | F10: 6 | G10: 12 | J10: 1 | K10: 2 | L10: 90 | M10: 180 | N10: 65 | O10: 80 | R10: Double progression. Add reps to reps_max, then add weight and return to reps_min. | S10: Hard sets close to failure drive growth. Compounds keep at least 1 rep in reserve.
A11: Hypertrophy|Rep | B11: Hypertrophy | C11: Rep | D11: 3 | E11: 4 | F11: 8 | G11: 20 | J11: 1 | K11: 2 | L11: 75 | M11: 105 | R11: Add reps, then slow the lowering phase, then move to a harder variation. | S11: Bodyweight sets need to be taken closer to failure than loaded ones.
A12: Hypertrophy|Time | B12: Hypertrophy | C12: Time | D12: 3 | E12: 3 | H12: 30 | I12: 60 | J12: 1 | K12: 2 | L12: 60 | M12: 90 | R12: Add seconds to 60, then add load or move to a harder position. | S12: Past 60 seconds the limit becomes endurance rather than muscle.
A13: Hypertrophy|Power | B13: Hypertrophy | C13: Power | D13: 2 | E13: 3 | F13: 3 | G13: 5 | J13: 3 | K13: 5 | L13: 120 | M13: 120 | R13: Do not chase growth here. Use it as a primer before heavy sets. | S13: Explosive lifts cannot be pushed near failure safely.
A14: Hypertrophy|Interval | B14: Hypertrophy | C14: Interval | D14: 1 | E14: 1 | H14: 600 | I14: 900 | J14: 4 | K14: 6 | R14: Hold steady. Do not add volume. | S14: Enough conditioning to stay fit, not enough to eat into recovery.
A15: Fat Loss|Load | B15: Fat Loss | C15: Load | D15: 2 | E15: 3 | F15: 8 | G15: 15 | J15: 1 | K15: 3 | L15: 45 | M15: 75 | N15: 60 | O15: 75 | R15: Keep the weight the same and cut rest, or hold the reps and add weight. Never let load fall. | S15: In a calorie deficit, lifting keeps the muscle you already have. Cut volume, never load.
A16: Fat Loss|Rep | B16: Fat Loss | C16: Rep | D16: 2 | E16: 3 | F16: 12 | G16: 20 | J16: 1 | K16: 3 | L16: 45 | M16: 60 | R16: Add reps or shorten rest. Can be run as a circuit. | S16: Keeps heart rate up while still loading the muscle.
A17: Fat Loss|Time | B17: Fat Loss | C17: Time | D17: 2 | E17: 3 | H17: 30 | I17: 45 | J17: 1 | K17: 3 | L17: 30 | M17: 45 | R17: Add seconds or reduce rest. | S17: Cheap to recover from and keeps total work high.
A18: Fat Loss|Power | B18: Fat Loss | C18: Power | D18: 4 | E18: 6 | H18: 15 | I18: 20 | J18: 3 | K18: 5 | L18: 40 | M18: 60 | R18: Add rounds, not reps per round. | S18: Capping the work interval keeps technique intact as fatigue builds.
A19: Fat Loss|Interval | B19: Fat Loss | C19: Interval | H19: 20 | I19: 40 | L19: 40 | M19: 60 | P19: 6 | Q19: 10 | R19: Add rounds, then extend the work interval, then cut rest. | S19: Short hard intervals. Effort around 8 out of 10, never all out.
A20: General Fitness|Load | B20: General Fitness | C20: Load | D20: 2 | E20: 3 | F20: 8 | G20: 15 | J20: 2 | K20: 3 | L20: 60 | M20: 90 | N20: 55 | O20: 70 | R20: Add reps or a small amount of weight whenever the last set feels easy. | S20: Leaving reps in reserve keeps soreness low and keeps the user turning up.
A21: General Fitness|Rep | B21: General Fitness | C21: Rep | D21: 2 | E21: 3 | F21: 8 | G21: 15 | J21: 2 | K21: 3 | L21: 60 | M21: 60 | R21: Add reps, then progress the variation. | S21: The goal is a habit that survives exam period.
A22: General Fitness|Time | B22: General Fitness | C22: Time | D22: 2 | E22: 3 | H22: 20 | I22: 45 | J22: 2 | K22: 3 | L22: 45 | M22: 60 | R22: Add seconds. | S22: Builds trunk endurance and postural tolerance.
A23: General Fitness|Power | B23: General Fitness | C23: Power | D23: 2 | E23: 3 | F23: 5 | G23: 8 | J23: 4 | K23: 6 | L23: 90 | M23: 90 | R23: Add reps only once the landing is quiet and controlled. | S23: Teaches force absorption, which protects knees and ankles. Skill first.
A24: General Fitness|Interval | B24: General Fitness | C24: Interval | H24: 30 | I24: 60 | L24: 60 | M24: 90 | P24: 3 | Q24: 5 | R24: Add rounds. | S24: Moderate effort, around 6 out of 10. Builds an aerobic base.

Sheet Progression Engine
A1: Progression Engine (runtime)
A2: How the backend adjusts reps, sets and load from logged performance. Runs at Generator Flow step 9 after every completed workout instance, reading set_logs and writing progression_state. Every adjustment is bounded by the Prescription Grid ranges and the Safety Rules: the engine may move a user within reps_min to reps_max and up to the S07 weekly load cap, and it may never take a user below a floor, above 88 percent 1RM, below 4 reps on a Load exercise, or past the exercise Min RIR. Progression only happens when it is safe: fatigue, missed reps and stop symptoms all pause or reverse it.
A4: rule_id | B4: adjustment | C4: condition | D4: engine_action | E4: writes_to_progression_state
A5: PR01 | B5: progress load (up) | C5: Loadable exercise. User hit the top of the rep range (reps_max) with the prescribed RIR or easier, for the required number of sessions (default 2 in a row) | D5: Add one increment: 2.5kg upper body, 5kg lower body, or 5 percent, whichever is smaller. Reset reps to reps_min. Capped by Safety Rule S07 (max 5 percent per week). | E5: progression_state.current_load_kg up, current_rep_target reset to reps_min, sessions_at_current=0, stall_count=0
A6: PR02 | B6: progress reps (up) | C6: Non-loadable exercise (bodyweight, band with no more tension), user hit reps_max at target RIR | D6: Add reps beyond reps_max up to a soft ceiling, then slow the lowering phase, then progress to a harder variation via Substitutions (higher skill, same group). | E6: current_rep_target up, or variation swap logged
A7: PR03 | B7: hold | C7: User completed the session inside the rep range but not at the top, at target RIR | D7: Repeat the same prescription next session. No change. | E7: sessions_at_current +1
A8: PR04 | B8: reduce (down) | C8: User missed reps_min, or reported RIR 0 or failure on 2+ sets, or form broke down | D8: Reduce load by 10 percent (loadable) or reps toward reps_min (non-loadable). Rebuild from there. Never drop below the exercise floor. | E8: current_load_kg down 10 percent, stall_count +1
A9: PR05 | B9: stall | C9: Same exercise fails to progress for 3 consecutive sessions (stall_count reaches 3) | D9: Trigger a deload on that exercise: cut sets 40 percent and load 10 percent for one session (Safety Rule F01 style), then resume. If it stalls again after the deload, offer a substitute of equal difficulty for variety. | E9: deload_count +1, stall_count reset to 0
A10: PR06 | B10: fatigue override | C10: User logs RPE 10 or failure on 3+ sets in a session, or flags poor sleep or a missed prior session | D10: Do not progress this session regardless of PR01/PR02. Apply Safety Rules F02/F03: hold or reduce, raise rir_min by 1. Progression resumes when fatigue clears. | E10: no progression written, fatigue flag noted
A11: PR07 | B11: new exercise starting load | C11: An exercise the user has never done (fresh program, or a swap) | D11: Do not guess heavy. Start at an estimate from a similar logged lift if one exists, otherwise start light at RIR 4 to 5 and let the user find the working weight over 2 sessions (Safety Rule P01). | E11: progression_state row created, first 2 sessions marked as calibration
A12: PR08 | B12: beginner ramp | C12: User is in their first 4 weeks | D12: Progress conservatively: rir_min stays at 2, load increments at the bottom of the range, add reps before load. Block Advanced and Power classes (Safety Rule P01). | E12: standard state writes, capped increments
A14: Load Increments by Equipment
A15: PR01 says 'add the smallest available increment'. What is available depends on the equipment, not the muscle. The engine rounds the target load to the nearest achievable increment for that equipment before writing it.
A16: equipment_type | B16: min_increment | C16: rounding_rule
A17: barbell | B17: 2.5 kg total | C17: Round to nearest 2.5 kg (1.25 kg plate per side). 5 kg jumps for lower-body compounds once past the beginner ramp.
A18: dumbbell | B18: 2 to 2.5 kg per hand | C18: Round to the gym's available dumbbell steps; many go up in 2 kg. If the next dumbbell is too big a jump, add reps first.
A19: fixed_machine | B19: 1 plate on the stack | C19: Round to one stack plate. If one plate is too large a jump, add reps or use the half-plate pin if present.
A20: cable | B20: 1 plate on the stack | C20: Same as machine. Cable stacks often start smaller, so increments are gentler.
A21: bodyweight | B21: add reps, then tempo, then harder variation | C21: No external load. Progress via PR02, not PR01.
A22: band | B22: next band level | C22: Discrete jumps; add reps within a band before moving up a level, the jump between bands is large.
A23: assisted | B23: reduce assistance by 2.5 to 5 kg | C23: Less assistance means more of your own bodyweight. Progress by removing assistance, not adding load.
A25: Non-weight progression: duration exercises progress by seconds up to the Time cap (60s), interval exercises by rounds then work-interval length, carries by distance or time, assisted exercises by reducing assistance. The engine reads measurement_type to know which value to move.

Sheet Safety Rules
A1: Safety and Programming Rules
A2: Applied after the Prescription Grid lookup, in ascending numeric priority (the rule_id prefix is a label, priority is the sort key). HARD_SAFETY rules can block or rewrite a session and are never overridden by any goal, preference or prompt. PROGRAM_DEFAULT and FATIGUE_ADJUSTMENT rules are coaching defaults with named exemptions.
A4: rule_id | B4: priority | C4: rule_type | D4: applies_to | E4: condition | F4: action | G4: plain_english
A5: S01 | B5: 10 | C5: HARD_SAFETY | D5: skill_level = Advanced | E5: user_experience below Advanced | F5: Do not serve. Walk the Substitutions list in priority order and return the first entry compatible with the user's skill level, equipment, restrictions and exclusion history. | G5: Advanced lifts are never given to a beginner. The app walks the swap list until it finds one the user can actually and safely do.
A6: S02 | B6: 20 | C6: HARD_SAFETY | D6: prescription_class = Power | E6: any goal | F6: Force rir_min to 2 or higher. End set if movement speed or landing quality drops. | G6: Explosive lifts are never taken to failure. A failed jump squat is a fall.
A7: S03 | B7: 30 | C7: HARD_SAFETY | D7: Failure Allowed = No | E7: any goal | F7: Force rir_min to the exercise Min RIR or higher. | G7: Free weight compounds, Power lifts and Advanced lifts always stop short of failure. Nobody fails a squat alone in a university gym.
A8: S04 | B8: 40 | C8: HARD_SAFETY | D8: prescription_class = Load | E8: reps below 4 or load above 88% 1RM | F8: Clamp reps_min to 4 and pct_1rm_max to 88. | G8: The app never prescribes a near maximal single, double or triple. That needs a coach and a spotter in the room.
A9: S05 | B9: 50 | C9: HARD_SAFETY | D9: all exercises | E9: user has not completed pre exercise screening | F9: Block program generation. Run the screening flow. Route on the outcome per the Screening Outcomes sheet. | G9: Everybody is screened before a single set is prescribed, and the screening outcome decides what happens next. Screening alone does not guarantee safety.
A10: S06 | B10: 60 | C10: HARD_SAFETY | D10: all exercises | E10: stop symptom reported: chest pain or discomfort, dizziness, fainting, unusual shortness of breath, palpitations, numbness or tingling, sharp joint pain | F10: End the session immediately. Show the stop message. Do not generate further sessions until the user confirms symptoms resolved, or professional clearance where the Screening Outcomes sheet requires it. | G10: Symptoms are never trained through. Chest pain, dizziness and fainting also prompt the user to seek medical advice.
A11: S07 | B11: 70 | C11: HARD_SAFETY | D11: prescription_class = Load | E11: weekly load increase | F11: Cap load increase at 5 percent per week per exercise, or 2.5kg upper and 5kg lower body, whichever is smaller. | G11: Slow progression is the safe kind. Big jumps are how people get hurt.
A12: S08 | B12: 80 | C12: HARD_SAFETY | D12: all exercises | E12: required equipment not available to the user | F12: Walk the Substitutions list and return the first compatible entry. | G12: The app never prescribes gear the user does not have.
A13: S09 | B13: 90 | C13: HARD_SAFETY | D13: Spotter Recommended = Yes | E13: user trains alone | F13: Serve the highest priority substitute that does not need a spotter, or attach the no spotter safety cue (no collars on bench, safeties set in the rack). | G13: Barbell bench and back squat variations get a spotter or a safe setup, never neither.
A14: P01 | B14: 100 | C14: PROGRAM_DEFAULT | D14: user_experience = Beginner | E14: first 4 weeks | F14: Force rir_min to 2. Block Advanced and Power classes. Start every load light, around RIR 4 to 5 in week one, and work up over two sessions. | G14: New lifters build the movement first, then the effort, then the load.
A15: P02 | B15: 110 | C15: PROGRAM_DEFAULT | D15: prescription_class = Load or Rep | E15: rest below 45 seconds outside Fat Loss circuits and Interval work | F15: Raise rest_sec_min to 45. | G15: A default, not a law. Fat Loss circuits and Intervals are exempt because short rest is the point there.
A16: P03 | B16: 120 | C16: PROGRAM_DEFAULT | D16: prescription_class = Time | E16: any goal | F16: Cap duration_sec_max at 60. | G16: Past a minute the hold trains endurance, not the target muscle. A preference, not a safety fact.
... A19: F03 | B19: 150 | C19: FATIGUE_ADJUSTMENT | D19: all exercises | E19: user reports poor sleep or a missed session | F19: Raise rir_min by 1 for that session. | G19: An easier session done beats a hard session skipped.

Sheet Screening Outcomes
A1: Screening Outcomes
A2: The pre exercise screening (modelled on the Adult Pre Exercise Screening System used in Australia) maps every user to exactly one outcome before anything is generated. Completing the screen does not itself guarantee safety, which is why outcomes route to professionals rather than to a softer program.
A4: outcome | B4: triggered_by | C4: generator_action | D4: note
A5: CLEAR | B5: No flags on the pre exercise screening questionnaire. | C5: Generate the program normally. | D5: No restriction.
A6: MODIFY_AND_CONTINUE | B6: A joint or soft tissue flag (screening q5) that the FOLLOW-UPS confirm is minor: not currently painful, not under active professional treatment, exercise not restricted, issue resolved or stable. Also: low activity history, mild niggles without current pain. | C6: Generate with modifications: raise rir_min by 1, block Power class, prefer low impact and machine or supported variations for the flagged region, exclude exercises the user marks as aggravating. Apply the flagged region's row from the Injury Modifications sheet to every session. | D6: Modifications stay on until the user reports 4 symptom free weeks.
A7: REQUIRE_PROFESSIONAL_CLEARANCE | B7: Flags needing a professional first: any cardiovascular, metabolic or renal condition; chest pain or unusual breathlessness with activity; dizziness or fainting; pregnancy or birth within 6 months; recent surgery; OR a joint/soft tissue problem the follow-ups show is currently painful, under active treatment, or exercise-restricted. | C7: Do not generate a program. Show a message directing the user to a GP, physiotherapist or accredited exercise professional. Unlock generation only after the user confirms clearance, then apply any conditions the professional sets. Pregnancy follows its own clearance path, it is never treated as a generic injury flag. | D7: The app never decides that a gentler workout is safe enough for a flagged medical condition. A professional does.
A8: DO_NOT_GENERATE | B8: Acute red flags: current chest pain, symptoms at rest, a professional has advised against exercise. | C8: Block program generation entirely. Advise the user to seek medical care. | D8: Hard stop.
A10: Joint flag follow-ups (asked only when screening q5 = Yes)
A11: A bare yes/no joint question cannot decide the route. When q5 is Yes, ask these and route on the answers. Any answer in the 'to clearance' column sends the user to REQUIRE_PROFESSIONAL_CLEARANCE. If all are in the 'to modify' column, route to MODIFY_AND_CONTINUE and store the affected region.
A12: follow_up_question | B12: answer_to_modify | C12: answer_to_clearance
A13: Is the problem painful right now? | B13: No / mild and settling | C13: Yes, currently painful
A14: Is it being treated by a health professional? | B14: No / discharged | C14: Yes, under active treatment
A15: Have you been told to limit or avoid exercise? | B15: No | C15: Yes, exercise restricted
A16: Is the issue resolved, or still active? | B16: Resolved or stable | C16: Still active / flaring
A17: Which movements make it worse? (free text) | B17: Stored as affected_region for SW02 filtering | C17: -
A19: Free-text red-flag scan ('anything else we should know?')
A20: The optional free-text box is scanned before it is treated as harmless. If it mentions a cardiac, neurological, respiratory or metabolic condition, pregnancy, recent surgery, or medical-advice language ('my doctor said', 'I was told not to'), route the user to REQUIRE_PROFESSIONAL_CLEARANCE and do not generate until cleared. Otherwise store it as context. It is never a substitute for the seven screening questions.

Sheet Injury Modifications
A1: Injury Modifications
A2: Deterministic rules for the MODIFY_AND_CONTINUE branch. When screening routes a user to MODIFY (a joint or soft-tissue flag the follow-ups confirmed is minor), the generator reads the row for the flagged region and applies it to every session. This is a fixed lookup, not model judgement: the same flag always produces the same constraints. The user's free-text 'which movements make it worse' adds nuance on top, but the floor below is guaranteed. exclude_ids are removed from selection entirely; downgrade means the exercise stays eligible only if no excluded_free alternative fills the slot, and then at raised RIR. All flagged-region exercises get rir_bump added to rir_min. This never overrides a HARD_SAFETY rule or a REQUIRE_PROFESSIONAL_CLEARANCE outcome.
A4: region | B4: matches_stress_region | C4: avoid_patterns | D4: prefer | E4: rir_bump | F4: exclude_ids | G4: downgrade_ids | H4: review_after | I4: coach_note
A5: lower_back | B5: lower_back | C5: Hinge (heavy), loaded spinal flexion/rotation under load | D5: Supported=Yes, machine and chest-supported variations, hip-dominant work without spinal load | E5: 1 | F5: BK01, BK10, BK02, SH01, CO06 | G5: HG01, BK12, BK13, QD01, QD06, HG07, HG08, FB01, FB02, FB07, FB11, CO14 | H5: 4 weeks | I5: The big free-weight hinges and standing barbell work come out first. Keep training the muscles through supported and machine options: chest-supported rows, leg press, hip thrust, back extension held short of end range.
A6: knee | B6: knee | C6: Deep knee flexion under load, high-impact jumping, plyometrics | D6: Supported=Yes, machine leg work, partial-range and hip-dominant options, Impact=Low only | E6: 1 | F6: QD13, FB03, FB08, FB10, HG06 | G6: QD01, QD06, QD03, QD04, QD08, QD11, QD10, QD14, FB05, FB06, FB09 | H6: 4 weeks | I6: Cut jumping and deep loaded squats. Keep quads and hamstrings via leg press in a comfortable range, leg extension and curl machines, and hinge patterns that spare the knee.
A7: shoulder | B7: shoulder | C7: Overhead pressing, wide-grip and deep pressing, behind-neck work | D7: Neutral-grip and supported presses, rows over overhead work, partial range, Impact=Low | E7: 1 | F7: SH01, SH08, CH10, BI05 | G7: SH02, SH07, SH11, CH01, CH09, CH03, TR01, TR05, TR06, BK04, FB03, FB04, FB09 | H7: 4 weeks | I7: Overhead and heavy flat pressing come out first. Keep chest and shoulders through neutral-grip dumbbell presses, machine presses in a pain-free range, and plenty of pulling. Rear-delt and rotator-friendly work is encouraged.
A8: wrist | B8: wrist | C8: Loaded wrist extension, straight-bar pressing and curling, push-up positions | D8: Neutral-grip and machine options, straps or handles that keep the wrist neutral, avoid full weight-bearing on the hand | E8: 1 | F8: CH04, TR06, SH08 | G8: CH01, CH09, TR01, SH01, BI01, TR05 | H8: 4 weeks | I8: Take out push-up positions and straight-bar work that force wrist extension. Machines, neutral-grip dumbbells and cables let the user keep training with a neutral wrist.
A9: hip | B9: hip | C9: Deep hip flexion under load, wide stance, explosive hinging | D9: Supported and machine work, moderate range, controlled tempo, Impact=Low | E9: 1 | F9: QD13, FB01, FB11, FB08 | G9: QD01, QD06, HG01, HG07, HG08, QD03, QD04, QD11, HG13 | H9: 4 weeks | I9: Cut explosive and deep-range hip work. Keep legs and glutes through machine and supported options in a comfortable range, and single-leg work only if pain-free.
A10: ankle | B10: ankle | C10: High-impact jumping, hopping, running-based conditioning | D10: Low-impact conditioning (bike, rower, swim), seated calf work, stable-stance lifts | E10: 1 | F10: CA04, FB03, FB08, FB10, QD13 | G10: QD03, QD04, QD08, QD11, FB05, FB06, CA01, CA03 | H10: 4 weeks | I10: Remove jumping and running-based conditioning. Swap to bike or rower for cardio, seated calf raises, and lifts taken from a stable stance. Standing calf and lunges return once pain-free.
A12: How the generator applies a row
A13: 1. Screening + follow-ups route the user to MODIFY_AND_CONTINUE and record the affected region(s) from the Step 7 injury chip and the 'which movements make it worse' free text.
A14: 2. For each flagged region, load its row here. Remove every exclude_id from the candidate pool. Mark every downgrade_id as last-resort (used only if a slot cannot otherwise be filled, and then at rir_min + rir_bump).
A15: 3. Within every remaining slot, prefer candidates matching the 'prefer' column (Supported=Yes, Impact=Low, machine/neutral-grip as specified). Add rir_bump to rir_min for any exercise whose Stress Regions include matches_stress_region.
A16: 4. If removing exclude_ids empties a required slot, walk the Substitutions list to the first compatible, non-excluded exercise. A required slot is never left unfilled; it is filled with a safer option.
A17: 5. The free-text answer refines but never loosens the row: it can exclude more, never re-include an exclude_id.
A18: 6. review_after: the modifications lift only when the user reports the region symptom-free for the stated period. Until then they persist on every regenerated session. Re-flagging the region resets the clock.
A19: 7. Multiple regions stack: apply every flagged row. If the combined exclusions make a goal's volume impossible, reduce volume before re-including any excluded exercise, and tell the user their program is modified for their injuries.
A21: Scope limit: this sheet handles minor, self-managed flags that screening cleared for training. Anything painful now, under treatment, exercise-restricted or still active routes to REQUIRE_PROFESSIONAL_CLEARANCE and no program generates. These modification rules are a starting safety floor and must be reviewed by an accredited exercise professional before launch.

Sheet Age Routing
A1: Age Routing
A2: Age decides which screening pathway runs, and it is collected as date_of_birth, never a defaulted number. Under-18s do not receive the adult screen. 16 to 17 year olds follow a young-person pathway with guardian consent and conservative training defaults. Under-16 is out of scope for launch and blocked. This routing runs before the screening questions.
A4: age_band | B4: ages | C4: pathway | D4: stored_fields | E4: note
A5: adult | B5: 18 and over | C5: Standard adult pre-exercise screening (7 questions). Route per Screening Outcomes. | D5: screening_version = adult_v1 | E5: No guardian consent required.
A6: young_person | B6: 16 to 17 | C6: Use the young-person screening pathway (ESSA-style youth screen), not the adult flow. Require guardian consent before any program generates. Conservative defaults: block Advanced and Power classes, rir_min +1, load increments at the bottom of the range. | D6: screening_version = youth_v1, guardian_consent_required = true | E6: A minor is never silently defaulted into the adult flow.
A7: under_16 | B7: Under 16 | C7: Do not generate a program. The platform is not designed or screened for under-16s. Show a message explaining this. | D7: screening_version = none, blocked = true | E7: Hard stop. Out of scope for launch.
A8: unverified | B8: Age not provided or not verified | C8: Do not generate. Prompt for date of birth. Age is never defaulted for screening purposes. | D8: age_verified = false | E8: The old 'default to 20' behaviour is removed.

Sheet Splits
A1: Training Splits
A2: The splits the generator can serve. day_structure is pipe separated day types, each mapping to a Session Templates row set. best_for_goals and experience are pipe separated tokens, 'All' matches everything. Conditioning is a first class day type (Cond) with its own template, so Interval prescriptions always have a deterministic home. Rest days fill the remaining calendar days per Schedule Rules.
A4: split_id | B4: name | C4: days_min | D4: days_max | E4: day_structure | F4: best_for_goals | G4: experience | H4: why
A5: FB1 | B5: Full Body x1 | C5: 1 | D5: 1 | E5: Full | F5: All | G5: All | H5: One quality full body session. Not optimal, vastly better than nothing, and honest about it.
A6: FB2 | B6: Full Body x2 | C6: 2 | D6: 2 | E6: Full|Full | F6: All | G6: All | H6: Every muscle twice a week in two sessions. The most efficient use of two gym days that exists.
A7: FB3 | B7: Full Body x3 | C7: 3 | D7: 3 | E7: Full|Full|Full | F7: All | G7: Beginner|Intermediate | H7: Three full body days with a rest day between each. The default for beginners.
A8: FB3C | B8: Full Body x3 + Conditioning | C8: 4 | D8: 4 | E8: Full|Full|Full|Cond | F8: Fat Loss|General Fitness | G8: All | H8: The beginner friendly four day week: three full body days plus a dedicated conditioning day.
A9: PPL3 | B9: Push Pull Legs (rotating) | C9: 3 | D9: 3 | E9: Push|Pull|Legs | F9: Hypertrophy|General Fitness | G9: Intermediate|Advanced | H9: Classic three way split, each muscle once per week directly. Focused sessions over maximum frequency.
A10: UL4 | B10: Upper Lower | C10: 4 | D10: 4 | E10: Upper|Lower|Upper|Lower | F10: All | G10: All | H10: Every muscle twice a week with sessions under an hour. The best default for four days.
A11: UL4C1 | B11: Upper Lower + Conditioning | C11: 5 | D11: 5 | E11: Upper|Lower|Upper|Lower|Cond | F11: Strength|Fat Loss|General Fitness | G11: All | H11: Four lifting days plus a dedicated conditioning day. The five day answer outside hypertrophy.
A12: UL4C2 | B12: Upper Lower + 2 Conditioning | C12: 6 | D12: 6 | E12: Upper|Lower|Upper|Lower|Cond|Cond | F12: Fat Loss|General Fitness | G12: Intermediate|Advanced | H12: Four lifting days, two conditioning days. For users who want six active days without six lifting days.
A13: UL5 | B13: Upper Lower + Focus | C13: 5 | D13: 5 | E13: Upper|Lower|Upper|Lower|Focus | F13: Hypertrophy | G13: Intermediate|Advanced | H13: Upper Lower base with a fifth day built entirely from the user's focal points.
A14: PPL6 | B14: Push Pull Legs x2 | C14: 6 | D14: 6 | E14: Push|Pull|Legs|Push|Pull|Legs | F14: Hypertrophy | G14: Intermediate|Advanced | H14: Everything twice a week at high volume. Only for users who genuinely train six days.

Sheet Custom Split Rules
A1: Custom Split Rules
A2: What happens when the user wants a structure the Splits sheet does not list, like Push Pull Legs Push. The design principle: a custom split compiles down to the same day_structure format as a preset, is validated by these rules, and then flows through Session Templates, Weekly Volume, Prescription Logic and Safety Rules identically. No special cases downstream.
A4: rule_id | B4: name | C4: rule | D4: plain_english
A5: CS01 | B5: allowed building blocks | C5: A custom split is any ordered sequence of known day types (Push, Pull, Legs, Upper, Lower, Full, Focus, Cond) with length equal to the user's lifting days. It is stored as a day_structure string, exactly like the preset splits, so every downstream sheet works unchanged. | D5: Push Pull Legs Push is just 'Push|Pull|Legs|Push'. Nothing downstream needs to know it was custom.
A6: CS02 | B6: coverage check | C6: Every major muscle group must be hit directly at least once per week. If the sequence leaves a muscle at zero (Push Push Pull Push has no leg work), warn the user, and offer to convert one repeated day. If they insist, add the missing pattern as required slots on the closest day and note it on the program. | D6: The user can bias hard toward what they love, but nothing gets trained zero times without them being told.
A7: CS03 | B7: repeat spacing | C7: Repeated day types obey SCH03: at least 48 hours apart. 'Push|Push|Pull|Legs' is rearranged or rejected, 'Push|Pull|Legs|Push' is fine. | D7: You can press twice a week, just not on consecutive days.
A8: CS04 | B8: volume is shared, not doubled | C8: When a day type repeats, the weekly set budget for its muscles is split across the instances, not paid twice. The second instance also draws different exercises: the generator excludes slot picks already used that week and fills from different angles (flat becomes incline, barbell becomes dumbbell or cable). | D8: A second Push day means more variety at the same weekly budget, unless the muscle is a declared focal point, in which case the focal adjustment from Weekly Volume applies on top.
A9: CS05 | B9: caps still apply | C9: Weekly Volume caps, all HARD_SAFETY rules, screening outcomes and the session budget apply to custom splits with no exceptions. A custom split changes which days exist, never how hard any muscle may be pushed. | D9: Custom means custom structure, not custom safety.
A10: CS06 | B10: free text mapping | C10: If the user describes a split in words ('bro split', 'chest day Monday', 'arms twice a week'), the AI maps it to day types: a single muscle day maps to a Focus day for that muscle, 'arms twice' adds Biceps and Triceps as focal points on two days. If it cannot map the request, it offers the two nearest presets and explains the difference in one sentence each. | D10: Whatever the user asks for, they leave with a valid day_structure string. For common de-emphasis requests (e.g. 'legs once a week') use the Custom Split Resolution table for a deterministic day_structure rather than choosing freehand.
A11: CS07 | B11: experience gate | C11: Custom splits are offered to Intermediate and Advanced users. Beginners asking for one get it honoured where CS02 passes, with a one line note that the preset would serve them better, and never more push back than that. | D11: Guide, do not gatekeep. It is their program.

Sheet Custom Split Resolution
A1: Custom Split Resolution
A2: Turns a fuzzy structural request into a specific day_structure, so the same request always resolves the same way. The AI matches the user's day count and what they want to de-emphasise or emphasise, reads the resolved day_structure, then validates it through Custom Split Rules (coverage, 48-hour spacing, shared volume). If the user's phrasing does not match a row, offer the two nearest rows and let them pick. The resolved structure still passes through every safety and volume rule unchanged. This table decides STRUCTURE only, never how hard anything is trained.
A4: days_per_week | B4: user_request | C4: resolved_day_structure | D4: note
A5: 2 | B5: none / balanced | C5: Full|Full | D5: Two days is always full body. Nothing to bias.
A6: 3 | B6: none / balanced | C6: Full|Full|Full | D6: Default 3-day. Everything 3x if beginner, or PPL by preference.
A7: 3 | B7: legs once | C7: Upper|Push|Lower | D7: One lower day, two upper-focused days. Legs hit once, directly.
A8: 3 | B8: upper once / legs focus | C8: Lower|Upper|Lower | D8: Two lower days, one upper day. Upper muscles hit once, legs twice.
A9: 3 | B9: push emphasis | C9: Push|Pull|Lower | D9: One of each, push gets the freshest day.
A10: 4 | B10: none / balanced | C10: Upper|Lower|Upper|Lower | D10: Default 4-day. Everything twice.
A11: 4 | B11: legs once | C11: Push|Pull|Upper|Lower | D11: One lower day, three upper-focused days. Legs hit once, upper muscles twice or more.
A12: 4 | B12: upper once / legs focus | C12: Lower|Lower|Push|Pull | D12: Two lower days plus push and pull. Legs emphasised.
A13: 4 | B13: push/pull preference (2 push 1 pull 1 leg) | C13: Push|Pull|Push|Lower | D13: Honours a push-biased week with legs still once.
A14: 5 | B14: none / balanced | C14: Upper|Lower|Upper|Lower|Focus | D14: Default 5-day with a focal day.
A15: 5 | B15: legs once | C15: Push|Pull|Upper|Focus|Lower | D15: One lower day, upper volume spread across four days.
A16: 5 | B16: legs focus | C16: Lower|Upper|Lower|Push|Pull | D16: Two lower days across five.
... A18: 6 | B18: legs once | C18: Push|Pull|Upper|Push|Pull|Lower | D18: Legs once across six days, everything else high frequency.

Sheet Split Selector
A1: Split Selector
A2: Decision table. Match on days_per_week, then experience, then goal, first matching row wins. experience and goal are pipe separated tokens, 'All' matches everything. Focal points never change the split, they change slot filling and Weekly Volume distribution.
A4: days_per_week | B4: experience | C4: goal | D4: split_id | E4: reason
A5: 1 | B5: All | C5: All | D5: FB1 | E5: One day only ever gets full body.
A6: 2 | B6: All | C6: All | D6: FB2 | E6: Two days, full body both.
A7: 3 | B7: Beginner | C7: All | D7: FB3 | E7: Beginners get the pattern practice of three full body days.
A8: 3 | B8: Intermediate|Advanced | C8: Strength|General Fitness|Fat Loss | D8: FB3 | E8: Frequency beats session focus for these goals.
A9: 3 | B9: Intermediate|Advanced | C9: Hypertrophy | D9: FB3 | E9: Full body three times hits every muscle at least twice a week, the current strength standard. PPL3 stays available as an opt-in preference for users who prefer it.
A10: 4 | B10: All | C10: Fat Loss | D10: FB3C | E10: Three lifting days plus a real conditioning day suits a deficit better than four lifting days.
A11: 4 | B11: All | C11: Strength|Hypertrophy|General Fitness | D11: UL4 | E11: Upper Lower is the four day answer.
A12: 5 | B12: Beginner | C12: All | D12: UL4C1 | E12: A beginner's fifth day is conditioning, not more lifting.
A13: 5 | B13: Intermediate|Advanced | C13: Hypertrophy | D13: UL5 | E13: The fifth day is built from focal points.
A14: 5 | B14: Intermediate|Advanced | C14: Strength|General Fitness|Fat Loss | D14: UL4C1 | E14: Four lifting days plus one conditioning day.
A15: 6 | B15: Beginner | C15: All | D15: FB3C | E15: Beginners are not served six training days. Four is the ceiling.
A16: 6 | B16: Intermediate|Advanced | C16: Hypertrophy | D16: PPL6 | E16: Six real training days, everything twice.
A17: 6 | B17: Intermediate|Advanced | C17: Strength|General Fitness|Fat Loss | D17: UL4C2 | E17: Four lifting days, two conditioning days.

Sheet Goal Change
A1: Goal Change (runtime)
A2: What happens when the user changes their goal mid-program. The engine re-runs the parts of the Generator Flow that depend on goal (split selection, volume budget, prescription) while preserving everything that does not (logged loads, progression history, schedule, screening). The user's strength gains and history are never thrown away by a goal change, and intensity never spikes: a single easy transition week absorbs the shift. A goal change always creates a new program version.
A4: rule_id | B4: phase | C4: trigger_or_scope | D4: engine_action | E4: principle
A5: GC01 | B5: detect | C5: User tells the coach they want a different goal, or edits it in settings | D5: Confirm the new canonical goal (Strength, Hypertrophy, Fat Loss, General Fitness) and that they want to change now versus at the next block. | E5: Ask once, do not nag. The user owns their goal.
A6: GC02 | B6: re-select split | C6: New goal may change the best split (e.g. Fat Loss favours a conditioning day, Hypertrophy favours PPL or focus) | D6: Re-run the Split Selector with the new goal and the user's existing days and experience. If the split_id changes, show the user the new structure before applying. | E6: The calendar and commitments carry over, only the day structure may change.
A7: GC03 | B7: re-budget volume | C7: Weekly set targets differ by goal | D7: Re-read Weekly Volume for the new goal and experience. Re-run reconciliation. Re-apply focal points and commitment cuts. | E7: Volume shifts gradually, do not spike total sets more than 20 percent week over week.
A8: GC04 | B8: re-prescribe | C8: Each exercise's sets, reps, RIR and rest come from the Goal|Class grid row | D8: Look up the new Goal|Class prescription for every exercise in the program. Re-clamp against Min RIR, Failure Allowed and all Safety Rules. | E8: Exercise selection can largely stay; the prescription around it changes.
A9: GC05 | B9: preserve strength gains | C9: A user moving to Fat Loss should not lose the muscle they built | D9: Hold load where the grid allows, cut volume before load (Fat Loss rule), and keep the main compounds in the program even as accessory volume drops. | E9: Load is the last thing cut, always.
A10: GC06 | B10: preserve progression state | C10: The user's logged loads and history stay valid | D10: Do not reset progression_state on a goal change. Current loads carry into the new prescription; only the rep and set targets around them move. | E10: History is never wiped by a goal change.
A11: GC07 | B11: transition safely | C11: Big jumps in style (e.g. General Fitness to Strength) change intensity a lot | D11: Ease into the new intensity over one week: apply the new structure but keep rir_min one higher than target for the first week, then settle. | E11: One easy transition week protects against a sudden intensity spike.
A12: GC08 | B12: re-screen check | C12: A goal change is a natural moment to confirm nothing health-relevant has changed | D12: Ask if anything about their health has changed since onboarding. If yes, re-run the screening flow before applying the new goal. | E12: Screening stays current across the life of the program.
A13: GC09 | B13: version the program | C13: History and auditability | D13: A goal change creates a new program version (Data Schemas: programs.version up, superseded_by set on the old one). The old program stays in history. | E13: Nothing is destructive. The user can see what changed and when.

Sheet External Commitments
A1: External Commitments
A2: Fixed weekly activities declared at onboarding (day, type, intensity). The AI classifies free text into one commitment_type, the generator applies the numeric adjustments. volume_cut_sets applies across the muscles in volume_cut_muscles. adjacency_block_hours blocks Legs or Lower (or Pull, for climbing) that many hours either side. interval_slots_removed comes off the weekly conditioning budget. rir_penalty_next_day is added to rir_min on the following day. A commitment is training the app did not prescribe but the body still pays for.
A4: commitment_type | B4: examples | C4: load_profile | D4: volume_cut_muscles | E4: volume_cut_sets_min | F4: volume_cut_sets_max | G4: adjacency_block_hours | H4: interval_slots_removed | I4: rir_penalty_next_day | J4: notes
A5: basketball | B5: Basketball, netball, volleyball | C5: lower_body_impact|conditioning | D5: Quads|Hamstrings & Glutes | E5: 2 | F5: 4 | G5: 24 | H5: 1 | I5: 0 | J5: Never place a Legs or Lower day within adjacency_block_hours either side of the commitment.
A6: football | B6: Soccer, AFL, rugby, touch | C6: lower_body_impact|conditioning|contact | D6: Quads|Hamstrings & Glutes | E6: 3 | F6: 4 | G6: 24 | H6: 2 | I6: 1 | J6: Removes all standalone Interval work. The day after a match runs at rir_min plus rir_penalty_next_day.
A7: running | B7: Running, park run, athletics | C7: lower_body_impact|conditioning | D7: Quads|Hamstrings & Glutes | E7: 2 | F7: 4 | G7: 24 | H7: 1 | I7: 0 | J7: Adjacency applies to hard or long runs only. Easy runs need no adjustment beyond the Interval slot removal.
A8: racquet | B8: Tennis, badminton, squash | C8: lower_body_impact|unilateral|conditioning | D8: Quads|Hamstrings & Glutes | E8: 2 | F8: 2 | G8: 24 | H8: 1 | I8: 0 | J8: No extra rotation core work in commitment weeks, the sport supplies it.
A9: swimming | B9: Swimming, water polo | C9: full_body|low_impact_conditioning | E9: 0 | F9: 0 | G9: 0 | H9: 1 | I9: 0 | J9: Low impact, low recovery cost. Only the Interval slot removal applies.
A10: cycling | B10: Cycling, spin classes | C10: lower_body|low_impact_conditioning | D10: Quads | E10: 0 | F10: 2 | G10: 0 | H10: 1 | I10: 0 | J10: Cut Quads sets only when riding is hard or hilly, otherwise zero.
A11: climbing | B11: Climbing, bouldering | C11: upper_pull|grip | D11: Back|Biceps | E11: 2 | F11: 4 | G11: 24 | H11: 0 | I11: 0 | J11: Never place a Pull day within adjacency_block_hours. Grip heavy exercises (deadlifts, carries, rows) move away from climbing days. Counts as half an Interval session, round down.
A12: martial_arts | B12: Martial arts, boxing, BJJ | C12: full_body|conditioning|contact | D12: user_reported | E12: 2 | F12: 2 | G12: 0 | H12: 2 | I12: 1 | J12: Removes all standalone Interval work. Volume cut applies to whichever muscle the user reports as most worked.
A13: dance | B13: Dance, cheer, gymnastics | C13: full_body|lower_body_impact | D13: Quads|Hamstrings & Glutes | E13: 2 | F13: 2 | G13: 24 | H13: 1 | I13: 0 | J13: Adjacency applies before performances and hard rehearsals.
A14: physical_job | B14: Hospitality, labouring, retail on feet | C14: chronic_low_load | E14: 0 | F14: 0 | G14: 0 | H14: 0 | I14: 0 | J14: Start weekly volume at the bottom of the goal's range. Apply F03 after long shifts the user flags.
A15: social_sport | B15: Casual grade, under 1 hour, low intensity | C15: light_activity | E15: 0 | F15: 0 | G15: 0 | H15: 0 | I15: 0 | J15: Counts toward general activity only. No adjustment.
A16: other | B16: Anything not listed | C16: unknown | D16: user_reported | E16: 0 | F16: 2 | G16: 24 | H16: 1 | I16: 0 | J16: Default: treat as full body conditioning, ask the user which muscles it works, then reclassify into a row above.

Sheet Session Templates
A1: Session Templates
A2: How a single workout is assembled. Look up the day_type from the split's day_structure, fill slots in order. Filter tokens are pipe separated: 'Squat|Lunge' means the pattern is Squat OR Lunge. 'Compound>Isolation' means compound preferred, isolation allowed. FOCAL_1 and FOCAL_2 resolve to the user's declared focal points (eligible focal points: Chest, Back, Shoulders, Quads, Hamstrings & Glutes, Biceps, Triceps, Core, Calves. Full Body & Conditioning is not a focal point). Selection within a slot: filter by required_equipment_tags against the user's equipment, skill and exclusions, then weight by Primary Goal Fit, then focal points, then prefer already logged exercises. Required slots must fill, walking Substitutions if needed. Optional slots drop first on short sessions. Sets and reps per slot come from Prescription Logic. Compounds never sit after isolation work for the same muscle. Session budget: 4 to 6 exercises and 12 to 22 working sets at 45 to 60 minutes, 3 to 4 exercises and 9 to 14 sets at 30 minutes. Slot counts are a base, not a cap: Weekly Volume reconciliation may add or trim slots.
A4: slot_id | B4: day_type | C4: order | D4: slot_name | E4: muscle_group_filter | F4: movement_pattern_filter | G4: type_filter | H4: required | I4: note
A5: Full-1 | B5: Full | C5: 1 | D5: Squat compound | E5: Quads | F5: Squat|Lunge | G5: Compound | H5: Yes | I5: The biggest lift goes first, freshest.
A6: Full-2 | B6: Full | C6: 2 | D6: Push | E6: Chest | F6: Horizontal Push|Vertical Push | G6: Compound | H6: Yes | I6: Main press of the day.
A7: Full-3 | B7: Full | C7: 3 | D7: Pull | E7: Back | F7: Horizontal Pull|Vertical Pull | G7: Compound | H7: Yes | I7: Every push is matched by a pull.
A8: Full-4 | B8: Full | C8: 4 | D8: Hinge | E8: Hamstrings & Glutes|Back | F8: Hinge | G8: Compound | H8: Yes | I8: Hinge pattern every session.
A9: Full-5 | B9: Full | C9: 5 | D9: Isolation filler | E9: Shoulders|Biceps|Triceps | F9: Any | G9: Isolation | H9: Optional | I9: Filled when session time allows, rotated across the week.
A10: Full-6 | B10: Full | C10: 6 | D10: Core | E10: Core | F10: Any | G10: Isolation | H10: Yes | I10: Core finishes every full body day.
A11: Upper-1 | B11: Upper | C11: 1 | D11: Horizontal push | E11: Chest | F11: Horizontal Push | G11: Compound | H11: Yes | I11: Main press first.
A12: Upper-2 | B12: Upper | C12: 2 | D12: Horizontal pull | E12: Back | F12: Horizontal Pull | G12: Compound | H12: Yes | I12: Row to match the press.
A13: Upper-3 | B13: Upper | C13: 3 | D13: Vertical push | E13: Shoulders | F13: Vertical Push | G13: Compound | H13: Yes | I13: Overhead work.
A14: Upper-4 | B14: Upper | C14: 4 | D14: Vertical pull | E14: Back | F14: Vertical Pull | G14: Compound | H14: Yes | I14: Pulldown or chin up pattern.
A15: Upper-5 | B15: Upper | C15: 5 | D15: Biceps isolation | E15: Biceps | F15: Any | G15: Isolation | H15: Optional | I15: Arms fill remaining time.
A16: Upper-6 | B16: Upper | C16: 6 | D16: Triceps isolation | E16: Triceps | F16: Any | G16: Isolation | H16: Optional | I16: Arms fill remaining time.
... A47: Cond-4 | B47: Cond | C47: 4 | D47: Core | E47: Core | F47: Any | G47: Isolation | H47: Optional | I47: Low fatigue core to close.

Sheet Weekly Volume
A1: Weekly Volume Targets
A2: Hard weekly sets per muscle. The generator budgets at the week level first and lets sessions follow. Working sets at the prescribed RIR only, warm ups do not count.
A4: goal | B4: experience | C4: weekly_sets_min | D4: weekly_sets_max | E4: applies_to
A5: Hypertrophy | B5: Beginner | C5: 8 | D5: 12 | E5: Chest|Back|Quads|Hamstrings & Glutes|Shoulders
A6: Hypertrophy | B6: Intermediate | C6: 10 | D6: 16 | E6: Chest|Back|Quads|Hamstrings & Glutes|Shoulders
A7: Hypertrophy | B7: Advanced | C7: 12 | D7: 20 | E7: Chest|Back|Quads|Hamstrings & Glutes|Shoulders
A8: Strength | B8: All | C8: 6 | D8: 12 | E8: Counted per main lift pattern (squat, press, hinge, pull) rather than per muscle
A9: Fat Loss | B9: All | C9: 6 | D9: 10 | E9: Enough to keep muscle in a deficit. Volume is cut before load, never the reverse
A10: General Fitness | B10: All | C10: 6 | D10: 10 | E10: All major muscle groups
A12: Reconciliation: making the week hit the budget
A13: Session Template slot counts are a base, not the budget. After building all days, the generator reconciles each muscle against its weekly target in this order. This is what closes the gap between, say, one chest slot per Upper day and a 10 set weekly minimum.
A14: order | B14: rule | C14: detail
A15: 1 | B15: Fill sets up | C15: Raise sets on existing slots from sets_min toward sets_max for the under target muscle. Example: Intermediate Hypertrophy on UL4, chest at 3+3 = 6 sets, raise both Upper day chest slots to 4+4 = 8.
A16: 2 | B16: Add a slot | C16: Still under target: add one extra slot per session for that muscle, isolation preferred, respecting the session set budget. Example: add a fly on one Upper day and a second press on the other, 8 + 4 = 12 sets, inside the 10 to 16 window.
A17: 3 | B17: Trim overshoot | C17: Over target (PPL6 back can hit 18+ sets): reduce that muscle's later slots to sets_min, then drop its optional slots, then convert one direct slot to the week's most under target muscle.
A18: 4 | B18: Arms, calves, core | C18: Half the main muscle target, direct sets only. Indirect work from compounds is deliberately not counted in v1, so the generator slightly overcounts arms and delts. That is the safe direction to err.
A19: 5 | B19: Focal points | C19: Add 3 to 4 weekly sets to each focal muscle, remove the same number from the lowest priority muscle, hard cap 20 for any muscle.
A20: 6 | B20: Commitment cuts | C20: Apply External Commitments volume cuts after focal adjustments. Cuts and focal additions on the same muscle net off.
A21: 7 | B21: Floor | C21: Every major muscle keeps at least 4 direct or heavy indirect sets per week on any split. Nothing is trained zero times.

Sheet Schedule Rules
A1: Schedule Rules
A2: How day types are placed onto the user's actual calendar, including rest day calculation and fixed commitments. Applied in rule order after the split is chosen. Rest days are whatever remains after lifting days and commitments are placed, subject to the SCH02 floor.
A4: rule_id | B4: name | C4: rule | D4: plain_english
A5: SCH01 | B5: inputs | C5: At onboarding collect: which days the user can lift, which days carry fixed commitments, and the commitment type and intensity for each. | D5: The calendar is built around real life, not the other way round.
A6: SCH02 | B6: rest floor | C6: Every week keeps at least one day with no lifting and no declared commitment. If the user's schedule leaves zero empty days, drop the lowest priority lifting day. | D6: One genuine rest day per week is non negotiable.
A7: SCH03 | B7: spacing | C7: At least 48 hours between two sessions of the same day type, and between any two sessions that hit the same muscle group directly. Consecutive day pairs that work (Upper then Lower, Push then Pull, Push then Legs) are preferred when days are tight. | D7: Muscles grow between sessions, not during them.
A8: SCH04 | B8: commitment adjacency | C8: Apply the adjacency rules from External Commitments. Where a conflict cannot be avoided (user lifts Mon and Wed, basketball Tue), place the Upper or Push day next to the commitment and move Legs or Lower as far from it as the week allows. | D8: Legs never sit against a leg heavy sport if any other arrangement exists.
A9: SCH05 | B9: placement order | C9: Place day types onto the calendar in this order: Legs and Lower first (they have the most constraints), then Pull, then Push and Upper, then Full, then Focus, then standalone conditioning. | D9: The most constrained day gets first choice of calendar slots.
A10: SCH06 | B10: compression | C10: If commitments plus the rest floor leave fewer usable lifting days than the chosen split needs, re run the Split Selector with the reduced day count. Never delete individual days from a split, the split itself changes. | D10: A 4 day Upper Lower with a day removed is a broken program. A 3 day Full Body is a complete one.
A11: SCH07 | B11: missed session | C11: If a session is missed and the next scheduled session is more than 24 hours away, shift the week forward one day. Otherwise skip the missed session and continue, folding its 2 highest priority slots into the next compatible day if the session budget allows. | D11: The program bends instead of snapping. Nobody restarts a week because of one bad Tuesday.
A12: SCH08 | B12: recurring conflict | C12: If the same session is missed 3 weeks running, treat the day as unavailable, re run scheduling, and suggest the change to the user rather than silently punishing them. | D12: The schedule adapts to the user's real week, not their optimistic one.
A13: SCH09 | B13: exam and travel mode | C13: On a user flag, compress to the FB2 split at General Fitness volume for the flagged period, keep loads, and restore the previous program after. | D13: Two maintained sessions through exam block beat a perfect program that gets abandoned.
A14: SCH10 | B14: planned absence | C14: Any date inside an active planned_absence (Exam Survival Protocol) is exempt from SCH07 and SCH08: it never counts as a missed session, never triggers re-scheduling, and never penalises the user. | D14: A day you told us about in advance is not a day you failed to show up.

Sheet Exam Survival Protocol
A1: Exam Survival Protocol (planned absence)
A2: Lets a user declare a future date range (exam block, holiday, travel, placement, life event) AHEAD of time and choose what happens to training. This is the proactive twin of Schedule Rules SCH07: SCH07 reacts to a missed day, this plans for a known one. The user picks one mode when adding the dates. Each mode is a deterministic rule the generator applies to every session inside the range, then automatically restores the normal program after. Progress is protected: no mode below 'full_pause' loses strength, and even full_pause freezes rather than resets. The overriding aim: the user tells the app 'I can't train on these days' and does NOT lose progress or get punished for it.
A4: mode_id | B4: name | C4: user says | D4: what the generator does | E4: when to use / effect on progress | F4: intent
A5: full_pause | B5: Full pause | C5: 'I can't train at all these days' | D5: No sessions scheduled in the range. Program is frozen, not deleted. On return, resume the exact next session that was due, at the same loads. No progression happens during the pause. | E5: Up to 2 weeks loses almost nothing. Beyond ~2 weeks, the return week runs at rir_min +1 and 40 percent fewer sets for one week to ease back in (re-entry ramp), then normal. | F5: maintain
A6: maintenance | B6: Maintenance (lighter) | C6: 'Keep me ticking over, but easy' | D6: Replace the normal split with FB2 (two full-body sessions) across whatever days in the range the user can still train. Hold loads, cut sets ~40 percent, raise rir_min by 1. No new progression, no new maxes. | E6: This is the recommended default for an exam block. Two short easy sessions a week fully maintain strength and muscle with minimal time and fatigue. | F6: maintain
A7: minimal_movement | B7: Just keep moving | C7: 'No gym, but I don't want to sit still' | D7: No lifting. Schedule a daily low-effort movement prompt instead: a walk (target 20-40 min or a step goal), optional mobility. Logged as activity, not training. Zero fatigue cost, keeps the habit alive. | E7: For users who want the streak and the routine without gym time. Protects adherence, which is the thing most likely to break over exams. | F7: habit
A8: reduced_frequency | B8: Fewer days | C8: 'I can only make it once or twice' | D8: Keep the current split's content but compress to the 1 or 2 highest-value sessions per week for the range (prioritise full-body or the user's focal days). Hold loads, normal reps, slightly higher rir_min. | E8: Best when the user can still get to the gym occasionally and wants it to count. Uses the same compression logic as Schedule Rules SCH06. | F8: maintain
A9: active_rest | B9: Planned deload | C9: 'Use this as a break' | D9: Treat the range as a scheduled deload (Safety Rule F01): cut sets 40 percent, hold load, raise rir_min by 1, for up to one week. If the range is longer than a week, the remainder becomes full_pause. | E9: Turns an unavoidable gap into a productive recovery block. Often the user comes back stronger. | F9: recover
A10: no_change | B10: Keep it as is | C10: 'Just letting you know, don't change anything' | D10: No program change. The declared days are logged as known-busy so the missed-session logic (SCH07) does not treat them as failures or trigger SCH08 re-scheduling. | E10: For users who will train anyway but want the app to stop nagging about 'missed' days. | F10: none
A12: Range handling and restore
A13: - Declared as a date range with a mode. Multiple ranges can be stored (e.g. two exam blocks and a holiday). Overlapping ranges take the more conservative mode.
A14: - During the range, all other rules still apply: HARD_SAFETY rules are never relaxed, screening state is unchanged, and a stop symptom still triggers S06 even in maintenance mode.
A15: - On the day the range ends, the normal program restores automatically. If the pause was longer than ~2 weeks, a one-week re-entry ramp runs first (rir_min +1, sets cut 40 percent) before full resumption.
A16: - progression_state is never wiped by an absence. Loads on return are the loads from before the range. Long pauses adjust the first week's intensity, not the stored loads.
A17: - The declared range suppresses the missed-session penalties (SCH07/SCH08) for those dates, so a planned absence never counts as a failure or forces a schedule re-run.
A18: - The user can edit or cancel a future range any time before it starts, and can end it early on return.

Sheet Exam Protocol Build Spec
A1: Exam Protocol: Build Spec
A2: What Claude Code has to build and what changes on the platform to deliver the Exam Survival Protocol. This is the implementation companion to the rules sheet: the rules sheet says WHAT happens, this says WHERE it is built. The same split of concerns (rules on one sheet, build spec on another) can be used for any future feature.
A4: area | B4: component | C4: what to build | D4: build note
A5: Data model | B5: users.planned_absences[] | C5: Add a planned_absences array to the users doc (or a subcollection): each entry {absence_id, start_date, end_date, mode_id, note, created_at, status: upcoming|active|completed|cancelled}. | D5: Firestore schema change. Add to Data Schemas sheet users collection.
A6: Onboarding / settings | B6: Exam Survival Protocol entry point | C6: The 'More' card the user tapped opens a flow: pick date range on a calendar, pick one mode (the 6 modes from this sheet shown as cards with the plain-English 'user says' text), optional note, confirm. | D6: New screen. Reuse the mode names and descriptions verbatim from this sheet so the UI and backend never drift.
A7: Generator | B7: Range-aware session generation | C7: Before generating any session, the generator checks whether its date falls inside an active planned_absence. If so, it applies that mode's rule instead of the normal build. On range end, it flips status to completed and resumes normal generation, running the re-entry ramp if the pause exceeded 2 weeks. | D7: Generator Flow gains a check at step 4 (scheduling). No new step, an added condition.
A8: Scheduler | B8: Suppress missed-day penalties in range | C8: Schedule Rules SCH07/SCH08 must skip any date covered by a planned_absence so declared-busy days never register as missed sessions. | D8: Logic change in the scheduler, references this sheet.
A9: Notifications | B9: Pre-range and restore prompts | C9: Optional: a reminder the day before a range starts ('Exam mode kicks in tomorrow, here's your lighter plan') and on restore ('Welcome back, easing you in this week'). | D9: Push notification hooks. Nice-to-have, not required for launch.
A10: Coach AI | B10: Conversational entry | C10: The user can also trigger this by telling the coach ('I've got exams from the 10th to the 24th'). The AI maps it to a date range + suggested mode, confirms, and writes the planned_absence. Governed by the Coach AI Operating Rules consult order. | D10: AI reads this sheet. Add a row to the Operating Rules consult table.

Sheet Generator Flow
A1: Generator Flow
A2: The end to end order of operations for the workout engine. Steps 1 to 8 build the initial program, steps 9 to 14 run continuously as the user trains and their needs change. The AI layer and the Firestore backend follow these steps in order. No step overrides an earlier HARD_SAFETY outcome, and every runtime change (progression, swap, goal change) is re-clamped by the Safety Rules.
A4: step | B4: name | C4: what_happens | D4: reads_from
A5: 1 | B5: Screen | C5: Run the pre exercise screening. Route on the Screening Outcomes sheet. CLEAR and MODIFY_AND_CONTINUE proceed, everything else stops here. | D5: Screening Outcomes
A6: 2 | B6: Collect inputs | C6: Goal, lifting days available (which weekdays, not just how many), session length, experience, exact equipment, focal points (0 to 2), exercises to avoid, and fixed weekly commitments with day, type and intensity. | D6: Onboarding, External Commitments
A7: 3 | B7: Pick split | C7: Match days, experience and goal in the Split Selector, first row wins. If the user requests their own structure, build and validate it through Custom Split Rules instead. Either path outputs a day_structure string. | D7: Split Selector, Splits, Custom Split Rules
A8: 4 | B8: Schedule the week | C8: Place day types onto actual weekdays using Schedule Rules: rest floor, 48 hour spacing, commitment adjacency, placement order. Apply the volume and conditioning adjustments from External Commitments. If usable days shrink below the split's needs, return to step 3 with the reduced count. Before placing sessions, check for any active planned_absence (Exam Survival Protocol) covering these dates and apply its mode instead of the normal build. | D8: Schedule Rules, External Commitments, Exam Survival Protocol
A9: 5 | B9: Budget volume | C9: Set weekly sets per muscle from Weekly Volume, apply focal point adjustments and commitment deductions, cap at 20, floor at the minimum effective. | D9: Weekly Volume, External Commitments
A10: 6 | B10: Build each day | C10: Fill Session Template slots in order for each scheduled day type. Filter by equipment, skill and exclusions, weight by Primary Goal Fit and focal points, prefer exercises the user already logs. Repeated day types draw different exercises per CS04. | D10: Session Templates, Exercise Database, Custom Split Rules
A11: 7 | B11: Prescribe | C11: Look up Goal|Class in Prescription Logic per exercise. Clamp against Min RIR, Failure Allowed and every HARD_SAFETY rule, then apply PROGRAM_DEFAULT and FATIGUE_ADJUSTMENT rules. | D11: Prescription Logic, Safety Rules, Exercise Database
A12: 8 | B12: Set starting loads | C12: Week one starts light, around RIR 4 to 5, and finds the working weight over two sessions. The app never guesses a heavy starting weight. | D12: Safety Rules P01
A13: 9 | B13: Progress | C13: After every completed instance, run the Progression Engine: read set_logs, adjust reps, sets and load within the grid ranges and Safety Rules, write progression_state. Progression pauses on fatigue and reverses on missed reps. | D13: Progression Engine, Prescription Logic, Safety Rules
A14: 10 | B14: Swap on demand | C14: On any user request to change an exercise (dislike, pain, equipment, too hard, too easy, wants a specific lift), follow the Exercise Swaps playbook: walk Substitutions to the first compatible entry, re-prescribe it, re-clamp safety. A reported stop symptom is an S06 escalation, not a swap. | D14: Exercise Swaps, Substitutions, Safety Rules
A15: 11 | B15: Adapt the calendar | C15: Missed sessions follow SCH07, recurring misses follow SCH08, exam or travel flags follow SCH09. New or changed commitments re run step 4. | D15: Schedule Rules
A16: 12 | B16: Adjust and deload | C16: Watch logged RPE, failures and sleep flags. Apply F01 to F03. Every 6th week is an easy week by default. | D16: Safety Rules
... A18: 14 | B18: Goal change | C18: If the user changes their goal mid-program, follow the Goal Change playbook: re-run split selection, volume budget and prescription for the new goal, preserve logged loads and progression history, ease intensity over one transition week, and version the program. | D18: Goal Change, Split Selector, Weekly Volume, Prescription Logic

Sheet Data Schemas
A1: Data Schemas (Firestore reference)
A2: The dynamic side of the backend: what gets written as users train. This workbook is the static rules layer, these collections are where user state lives. Reference for the Firebase build, field names are the contract between the app, the generator and the AI layer.
A4: collection | B4: key | C4: fields | D4: purpose
A5: users | B5: uid (doc id) | C5: uid, display_name, date_of_birth, age_verified, sex, height_cm, weight_kg, goal_weight_kg, experience, goal, focal_points[] (max 2), days_available[], session_length_min, equipment_tier, equipment_tags[], trains_alone, excluded_exercise_ids[], preferred_exercise_ids[], affected_regions[], commitments[{day, commitment_type, intensity}], screening{version, outcome, answers{}, followups{}, guardian_consent, clearance_confirmed, date, conditions[]}, diet[], tight_budget, planned_absences[{absence_id, start_date, end_date, mode_id, note, status}] | D5: One document per user. Everything the generator reads at step 2 lives here.
A6: programs | B6: program_id | C6: uid, version, split_id or day_structure, custom (bool), schedule{weekday: day_type}, created_at, active, superseded_by, generation_audit[{step, rule_ids_applied, choices}] | D6: Immutable once generated. Changes create a new version so history is never lost. The audit array records which rules fired, which is the debugging and liability trail.
A7: workout_instances | B7: instance_id | C7: instance_id, program_id, uid, scheduled_date, day_type, status (planned|done|partial|missed|shifted), exercises[{slot_id, exercise_id, substituted_from, measurement_type, sets, reps_min, reps_max, duration_sec, work_sec, rest_sec, rounds, distance_m, load_kg_target, load_unit, assistance_kg, bodyweight_added_kg, band_level, tempo, side, rir_min}] | D7: One document per scheduled workout. This is what the app screen renders.
A8: set_logs | B8: log_id | C8: log_id, instance_id, uid, exercise_id, set_number, measurement_type, load_kg, load_unit, reps_done, duration_sec_done, work_sec_done, rounds_done, distance_m_done, assistance_kg, band_level, tempo, side, rir_reported, timestamp, pain_flag, stop_symptom | D8: One document per completed set or round. measurement_type says which value fields are meaningful, so timed holds, intervals, carries and assisted lifts all log cleanly. Raw material for progression, F01-F03 and S06.
A9: progression_state | B9: uid_exerciseId (doc id) | C9: current_load_kg, current_rep_target, last_progressed_at, sessions_at_current, stall_count, deload_count | D9: One document per user per exercise. Read at step 9, written after every completed instance.
A10: swap_history | B10: uid | C10: events[{from_id, to_id, reason (dislike | equipment | pain | skill), date}] | D10: Feeds exclusions: a dislike swap means the exercise is not served again, a pain swap also blocks it pending S06 clearance.
A11: flags | B11: uid | C11: stop_symptom_events[{symptom, date, resolved, cleared_by_professional}], deload_history[dates], missed_streaks{weekday: count} | D11: Drives S06, F01 and SCH08.

Sheet Onboarding Contract
A1: Onboarding Contract
A2: One row per onboarding field. This is the contract between the app wizard and the backend: raw_answer is what the user taps, canonical_value is what gets stored and read by the generator. Mappings are deterministic lookups in code, never inferred by the AI at generation time, so two users who tap identical answers always route identically. 'ask' fields must be collected in the wizard. 'infer_ok' fields may be defaulted and refined later in app.
A4: step | B4: field | C4: raw_answer_options | D4: maps_to_backend_field | E4: canonical_value | F4: policy | G4: feeds
A5: 1 | B5: name | C5: free text | D5: users.display_name | E5: string, fallback 'Athlete' | F5: ask | G5: Tone only
A6: 1 | B6: age (derived) | C6: computed from date_of_birth | D6: users.age | E6: int, never defaulted | F6: ask | G6: Age Routing, Nutrition
A7: 1 | B7: sex | C7: Male | Female | Other | D7: users.sex | E7: male | female | other | F7: ask | G7: Nutrition (calorie accuracy)
A8: 2 | B8: height_cm | C8: ruler, default 175 | D8: users.height_cm | E8: int cm | F8: ask | G8: Nutrition only
A9: 2 | B9: weight_kg | C9: dial, default 75 | D9: users.weight_kg | E9: float kg | F9: ask | G9: Nutrition, starting load sanity
A10: 2 | B10: goal_weight_kg | C10: dial, default 78 | D10: users.goal_weight_kg | E10: float kg | F10: ask | G10: Nutrition only
A11: 3 | B11: goal | C11: Build muscle | Lose fat | Get stronger | Stay healthy | D11: users.goal | E11: Build muscle=Hypertrophy; Lose fat=Fat Loss; Get stronger=Strength; Stay healthy=General Fitness | F11: ask | G11: Split Selector, Prescription Logic, Weekly Volume
A12: 3 | B12: focal_points | C12: Chest|Back|Shoulders|Arms|Legs|Glutes|Core|Abs (max 2, skippable) | D12: users.focal_points[] | E12: Arms=Biceps+Triceps; Legs=Quads; Glutes=Hamstrings & Glutes; Abs=Core; others map by name. Max 2, empty allowed | F12: infer_ok | G12: Session Templates (Focus), Weekly Volume focal adjustment, UL5
A13: 4 | B13: experience | C13: Beginner (<6mo) | Intermediate (6mo-3yr) | Advanced (3yr+) | D13: users.experience | E13: Beginner | Intermediate | Advanced | F13: ask | G13: Split Selector, Safety Rules P01, Weekly Volume
A14: 5 | B14: training_days | C14: weekday multi-tap, default Mon Wed Fri Sat | D14: users.days_available[] | E14: array of gym weekdays only, sport excluded; editable post-onboarding, scheduler re-plans on change | F14: ask | G14: Split Selector (count), Schedule Rules (placement)
A15: 5 | B15: session_length_min | C15: 30 | 45 | 60 | 75 | D15: users.session_length_min | E15: int minutes | F15: ask | G15: Session Templates budget (exercise and set count)
... A34: 10 | B34: motivation | C34: free text, optional | D34: users.motivation | E34: string or null | F34: infer_ok | G34: Tone only
A36: Notes for the build
A37: 1
A38: 5
A39: 7
A40: 7
A41: - Screening is the final onboarding step (step 12), placed after motivation but BEFORE the first program is generated. Generator Flow step 1 reads the stored screening outcome, so the screen must be completed at the end of onboarding and the result saved before generation runs. It gates generation via Safety Rule S05.
A42: - Screening is a real screen, not a Terms of Use clause: the answers must change what the app does, which a buried waiver cannot. The waiver checkbox sits on the same screen, on top of it, not instead of it.
A43: - REQUIRE_PROFESSIONAL_CLEARANCE and DO_NOT_GENERATE outcomes stop generation. The app shows a neutral message directing the user to a health professional and unlocks generation only after clearance is confirmed. No diagnosis language.
A44: - The 'anything else' free text on step 8 is an addition, never a replacement for the seven structured questions. It catches extra detail; it does not route on its own.
A45: - Every 'ask' row must be present before step 3 of the Generator Flow runs. Every 'infer_ok' row may be defaulted at generation and refined later in conversation with the AI.
A46: - All canonical mappings live in one code lookup, shared by the wizard and the generator, so onboarding answers and backend behaviour can never drift.

Sheet Example Week
A1: Example Week
A2: What the pipeline produces for one concrete user: Intermediate, Hypertrophy goal, 4 days, Basic Gym, no focal points, screening CLEAR. Split Selector returns UL4. Every exercise passes the Basic Gym and skill filters, prescriptions come from Hypertrophy rows of the grid, all sets at RIR 1 to 2, rest 90 to 180 sec on compounds and 60 to 90 on isolations. This sheet is illustrative only, the generator never reads it.
A4: day | B4: day_type | C4: slot_1 | D4: slot_2 | E4: slot_3 | F4: slot_4 | G4: slot_5 | H4: slot_6
A5: Day 1 | B5: Upper | C5: Dumbbell Bench Press 3x8-12 | D5: Seated Cable Row 3x8-12 | E5: Seated Dumbbell Shoulder Press 3x8-12 | F5: Lat Pulldown 3x10-12 | G5: Hammer Curl 2x10-15 | H5: Triceps Pushdown 2x10-15
A6: Day 2 | B6: Lower | C6: Goblet Squat 3x8-12 | D6: Romanian Deadlift 3x8-12 | E6: Split Squat 3x8-10 each | F6: Lying Leg Curl 3x10-15 | G6: Standing Calf Raise 2x10-15 | H6: Plank 3x30-45 sec
A7: Day 3 | B7: Rest
A8: Day 4 | B8: Upper | C8: Incline Dumbbell Press 3x8-12 | D8: Chest Supported Dumbbell Row 3x8-12 | E8: Arnold Press 3x8-12 | F8: Band Assisted Chin Up 3x6-10 | G8: Barbell Curl 2x8-12 | H8: Overhead Cable Extension 2x10-15
A9: Day 5 | B9: Lower | C9: Leg Press 3x8-12 | D9: Hip Thrust 3x8-12 | E9: Walking Lunge 3x10 each | F9: Seated Leg Curl 3x10-15 | G9: Seated Calf Raise 2x10-15 | H9: Dead Bug 3x8-10 each
A10: Day 6 | B10: Rest
A11: Day 7 | B11: Rest
A13: Scheduling Example: Same User, Basketball Every Monday
A14: day | B14: placed | C14: why
A15: Monday | B15: Basketball (commitment) | C15: Declared at onboarding. Classified as basketball: lower body impact plus conditioning.
A16: Tuesday | B16: Upper | C16: SCH04: the day after basketball gets Upper, never Legs. Adjacency handled.
A17: Wednesday | B17: Lower | C17: 48 hours clear of basketball on both sides. SCH05 placed this day first.
A18: Thursday | B18: Rest | C18: SCH02 rest floor.
A19: Friday | B19: Upper | C19: 48 hours after Tuesday's Upper, satisfies SCH03.
A20: Saturday | B20: Lower | C20: 48 hours after Wednesday's Lower, and two clear days before Monday's basketball.
A21: Sunday | B21: Rest | C21: Second rest day before the commitment.
A22: Volume note | B22: - | C22: External Commitments: weekly Quads and Hamstrings & Glutes budget reduced by 3 sets, one Interval slot removed because basketball already covers conditioning.
A25: Custom Split Example: User Requests Push Pull Legs Push
A26: check | B26: result
A27: CS01 compile | B27: Stored as 'Push|Pull|Legs|Push'. Downstream sheets unchanged.
A28: CS02 coverage | B28: All muscles covered: chest, shoulders and triceps twice, back, biceps and legs once. Passes, no warning.
A29: CS03 spacing | B29: Scheduled Mon Push, Tue Pull, Thu Legs, Sat Push. Both Push days more than 48 hours apart.
A30: CS04 volume | B30: Weekly chest, shoulder and triceps budget split across the two Push days. Second Push day draws different exercises: Monday gets Barbell Bench Press and Barbell Overhead Press, Saturday gets Incline Dumbbell Press and Arnold Press.
A31: CS05 caps | B31: All prescriptions, RIR floors and safety rules unchanged.

Sheet Rep Range Guide
A1: What The Rep Number Actually Means
A2: Reference material for the app, and for anything user facing. Reps are a proxy for load. That is the whole idea.
A4: Rep Range | B4: Roughly | C4: Primary Adaptation | D4: What It Feels Like | E4: Use It When | F4: The Catch
A5: 1 to 3 | B5: 90%+ of 1RM | C5: Maximal strength. Almost entirely neural. The muscle barely changes, the nervous system learns to recruit it | D5: Heavy, slow, total concentration. The bar moves whether you like it or not | E5: Testing a max, or peaking a strength block. Rare for a student population | F5: Highest technical and injury risk. Needs a spotter and a lift the user has done for months. Not for a remote app to prescribe casually
A6: 4 to 6 | B6: 80 to 90% | C6: Strength with a little size. The best all round strength range | D6: Hard from rep one. Speed drops noticeably on the last rep | E6: The default strength range. Where a compound lift should live in a strength block | F6: Fatiguing on the joints and the nervous system. Needs long rest, so sessions run long
A7: 6 to 12 | B7: 70 to 80% | C7: The classic hypertrophy range. Enough load for tension, enough reps for volume | D7: Burning by rep eight, genuinely hard by rep ten | E7: The default for most users on most exercises. If in doubt, prescribe here | F7: It is not magic. It is popular because it balances load and volume efficiently, not because the muscle counts reps
A8: 12 to 20 | B8: 60 to 70% | C8: Hypertrophy plus muscular endurance. Equal growth to the mid range IF taken close to failure | D8: A deep burn. The last few reps are grim and slow | E8: Isolation work, bodyweight exercises, anything where load cannot be added easily | F8: Most people stop well short of failure here because it is uncomfortable. Under effort, this range does very little
A9: 20+ | B9: Under 60% | C9: Muscular endurance, work capacity, local conditioning | D9: Cardiovascular before it is muscular. Lungs give up before the muscle | E9: Conditioning, circuits, warm ups, rehab | F9: Poor return on time for both strength and size. The set ends because you are out of breath, not because the muscle failed
A12: Rules That Override The Table Above
A13: Effort beats rep range | B13: For muscle growth, a set of 8 and a set of 20 produce similar results IF both are taken within a couple of reps of failure. A set of 8 at RIR 5 produces almost nothing. Proximity to failure is the variable that matters. Rep range mostly decides how unpleasant getting there is.
A14: Load cannot be faked for strength | B14: Strength is specific to heavy load. There is no rep scheme that makes a bodyweight squat build a heavy back squat. This is the hard ceiling for the 20 Rep class and 8 Time class exercises in the database, and the app should say so rather than pretend.
A15: Compounds get fewer reps and more rest | B15: A compound lift fatigues the whole system, so it goes first in the session, in a lower rep range, with longer rest. An isolation lift fatigues one muscle, so it goes last, higher reps, short rest. The Type column already carries this.
A16: Never take Power or Advanced exercises to failure | B16: A failed jump squat is a fall. A failed deadlift is a back injury. These exercises stop at RIR 2 or higher regardless of the user goal. This is a hard rule in the generator, not a suggestion.
A17: Weekly sets per muscle matter more than any single session | B17: Roughly 10 to 20 hard sets per muscle per week for growth, 6 to 10 for general fitness. The generator should budget at this level and let session structure follow, not the reverse.
A18: Fat loss does not change the lifting | B18: In a deficit, lifting exists to keep muscle. Keep the load, cut the volume, add conditioning separately. Turning the weights session into cardio is the single most common mistake and it costs the user the muscle they are trying to keep.
